[{"sekolah_id":"199d090c-9fde-4eae-93cc-1dc50eacdb7b","semester_id":"20222","nama":"PKBM TAMAN SISWA","nama_nomenklatur":null,"nss":null,"npsn":"P9970328","bentuk_pendidikan_id":27,"bentuk_pendidikan":"PKBM","alamat_jalan":"Desa Embacang Gedang","rt":1,"rw":null,"nama_dusun":"Embacang Gedang","kode_wilayah":"100299AA","kode_desa_kelurahan":"100299AA","desa_kelurahan":"Embacang Gedang","kode_kecamatan":"100299  ","kecamatan":"Kec. Tanah Sepenggal Lintas","kode_kabupaten":"100200  ","kabupaten":"Kab. Bungo","kode_provinsi":"100000  ","provinsi":"Prov. Jambi","kode_pos":null,"lintang":-1.3579008,"bujur":101.9132138,"nomor_telepon":"081273811278","nomor_fax":null,"email":"pkbm_tamansiswa@yahoo.com","website":"http://","kebutuhan_khusus_id":0,"kebutuhan_khusus":"Tidak ada","status_sekolah_id":"2","status_sekolah":"SWASTA","sk_pendirian_sekolah":"04","tanggal_sk_pendirian":"2018-04-10","status_kepemilikan_id":4,"status_kepemilikan":"Lainnya","yayasan_id":null,"yayasan":null,"sk_izin_operasional":"90 tahun 2018","tanggal_sk_izin_operasional":"2018-03-14","no_rekening":"3004195247","nama_bank":"BPD JAMBI","cabang_kcp_unit":"CABANG MUARA BUNGO","rekening_atas_nama":"P9970328 PKBM TAMAN SISWA","mbs":0,"luas_tanah_milik":600,"luas_tanah_bukan_milik":0,"kode_registrasi":"13235429957279","npwp":"845858299332000               ","nm_wp":"PKBM TAMAN SISWA","keaktifan":"1","flag":null,"daya_listrik":450,"kontinuitas_listrik":"1","jarak_listrik":0,"wilayah_terpencil":"0","wilayah_perbatasan":"0","wilayah_transmigrasi":"0","wilayah_adat_terpencil":"0","wilayah_bencana_alam":"0","wilayah_bencana_sosial":"0","partisipasi_bos":"1","waktu_penyelenggaraan_id":8,"waktu_penyelenggaraan":"Sehari Penuh/3 hari","sumber_listrik_id":2,"sumber_listrik":"PLN","sertifikasi_iso_id":9,"sertifikasi_iso":"Belum Bersertifikat","akses_internet_id":0,"akses_internet":"Tidak Ada","akses_internet_2_id":0,"akses_internet_2":"Tidak Ada","akreditasi":"B","create_date":"2018-04-12T10:52:35.143000","last_update":"2022-03-10T11:08:09.470000"},{"sekolah_id":"44d7fa88-a4d0-4d78-8199-96bc1dfd80d1","semester_id":"20222","nama":"KB CAHAYA","nama_nomenklatur":null,"nss":null,"npsn":"70007585","bentuk_pendidikan_id":2,"bentuk_pendidikan":"KB","alamat_jalan":"Dusun Sungai Tembang","rt":null,"rw":null,"nama_dusun":"Sungai Tembang","kode_wilayah":"100299AK","kode_desa_kelurahan":"100299AK","desa_kelurahan":"Sungai Tembang","kode_kecamatan":"100299  ","kecamatan":"Kec. Tanah Sepenggal Lintas","kode_kabupaten":"100200  ","kabupaten":"Kab. Bungo","kode_provinsi":"100000  ","provinsi":"Prov. Jambi","kode_pos":"37263","lintang":0.0,"bujur":0.0,"nomor_telepon":null,"nomor_fax":null,"email":null,"website":"http://","kebutuhan_khusus_id":0,"kebutuhan_khusus":"Tidak ada","status_sekolah_id":"2","status_sekolah":"SWASTA","sk_pendirian_sekolah":"32","tanggal_sk_pendirian":"2012-02-10","status_kepemilikan_id":3,"status_kepemilikan":"Yayasan","yayasan_id":null,"yayasan":null,"sk_izin_operasional":"503/1363/pnf-paud/dpmptsp/2020","tanggal_sk_izin_operasional":"2020-11-12","no_rekening":"3004193066","nama_bank":"BPD JAMBI","cabang_kcp_unit":"Cabang Ma Bungo","rekening_atas_nama":"70007585 KB CAHAYA","mbs":0,"luas_tanah_milik":596,"luas_tanah_bukan_milik":0,"kode_registrasi":"150610934812836","npwp":"026941021332000               ","nm_wp":null,"keaktifan":"1","flag":null,"daya_listrik":900,"kontinuitas_listrik":"1","jarak_listrik":0,"wilayah_terpencil":"0","wilayah_perbatasan":"0","wilayah_transmigrasi":"0","wilayah_adat_terpencil":"0","wilayah_bencana_alam":"0","wilayah_bencana_sosial":"0","partisipasi_bos":"1","waktu_penyelenggaraan_id":1,"waktu_penyelenggaraan":"Pagi/6 hari","sumber_listrik_id":2,"sumber_listrik":"PLN","sertifikasi_iso_id":9,"sertifikasi_iso":"Belum Bersertifikat","akses_internet_id":4,"akses_internet":"Telkomsel Flash","akses_internet_2_id":4,"akses_internet_2":"Telkomsel Flash","akreditasi":null,"create_date":"2021-02-06T06:00:00.147000","last_update":"2023-06-04T10:37:11.307000"},{"sekolah_id":"10d1925c-0c26-e111-88e2-8d3de0c8a95f","semester_id":"20222","nama":"SD NEGERI 050II LUBUK LANDAI","nama_nomenklatur":null,"nss":"101100221505","npsn":"10500635","bentuk_pendidikan_id":5,"bentuk_pendidikan":"SD","alamat_jalan":"Jalan Pasir Putih","rt":0,"rw":0,"nama_dusun":"Sungai Lilin","kode_wilayah":"100299AE","kode_desa_kelurahan":"100299AE","desa_kelurahan":"Gungai Lilin","kode_kecamatan":"100299  ","kecamatan":"Kec. Tanah Sepenggal Lintas","kode_kabupaten":"100200  ","kabupaten":"Kab. Bungo","kode_provinsi":"100000  ","provinsi":"Prov. Jambi","kode_pos":"37263","lintang":-1.396,"bujur":101.9493,"nomor_telepon":"082387835300","nomor_fax":null,"email":"sdn50_lubuklandai@yahoo.com","website":"http://","kebutuhan_khusus_id":0,"kebutuhan_khusus":"Tidak ada","status_sekolah_id":"1","status_sekolah":"NEGERI","sk_pendirian_sekolah":null,"tanggal_sk_pendirian":"1982-01-01","status_kepemilikan_id":1,"status_kepemilikan":"Pemerintah Pusat","yayasan_id":null,"yayasan":null,"sk_izin_operasional":"893 TAHUN 2001","tanggal_sk_izin_operasional":"1910-01-01","no_rekening":"3001765077","nama_bank":"BPD JAMBI...","cabang_kcp_unit":"BPD JAMBI CABANG MUARA BUNGO...","rekening_atas_nama":"DNBOSSDN50IILUBUKLANDAI...","mbs":1,"luas_tanah_milik":3617,"luas_tanah_bukan_milik":0,"kode_registrasi":"101785642477068","npwp":"001155928332000               ","nm_wp":"SD Negeri 50/II Lubuk Landai","keaktifan":"1","flag":"3  ","daya_listrik":1300,"kontinuitas_listrik":"1","jarak_listrik":0,"wilayah_terpencil":"0","wilayah_perbatasan":"0","wilayah_transmigrasi":"0","wilayah_adat_terpencil":"0","wilayah_bencana_alam":"0","wilayah_bencana_sosial":"0","partisipasi_bos":"1","waktu_penyelenggaraan_id":1,"waktu_penyelenggaraan":"Pagi/6 hari","sumber_listrik_id":2,"sumber_listrik":"PLN","sertifikasi_iso_id":9,"sertifikasi_iso":"Belum Bersertifikat","akses_internet_id":4,"akses_internet":"Telkomsel Flash","akses_internet_2_id":2,"akses_internet_2":"Telkom Speedy","akreditasi":"B","create_date":"2018-01-24T12:09:39.813000","last_update":"2022-03-10T11:08:09.470000"},{"sekolah_id":"50f6825c-0c26-e111-ada4-8d247540148b","semester_id":"20222","nama":"SD NEGERI 200II EMBACANG GEDANG","nama_nomenklatur":null,"nss":"101100204200","npsn":"10505082","bentuk_pendidikan_id":5,"bentuk_pendidikan":"SD","alamat_jalan":"Jln.lintas Sumatra Arah Padang","rt":0,"rw":0,"nama_dusun":"PERANTIAN BALAI","kode_wilayah":"100299AA","kode_desa_kelurahan":"100299AA","desa_kelurahan":"EMBACANG GEDANG","kode_kecamatan":"100299  ","kecamatan":"Kec. Tanah Sepenggal Lintas","kode_kabupaten":"100200  ","kabupaten":"Kab. Bungo","kode_provinsi":"100000  ","provinsi":"Prov. Jambi","kode_pos":"37216","lintang":-1.402,"bujur":102.0221,"nomor_telepon":"081366799432","nomor_fax":null,"email":"windikusumawati04@gmail.com","website":"http://","kebutuhan_khusus_id":0,"kebutuhan_khusus":"Tidak ada","status_sekolah_id":"1","status_sekolah":"NEGERI","sk_pendirian_sekolah":null,"tanggal_sk_pendirian":"1979-08-07","status_kepemilikan_id":2,"status_kepemilikan":"Pemerintah Daerah","yayasan_id":null,"yayasan":null,"sk_izin_operasional":"-","tanggal_sk_izin_operasional":"1910-01-01","no_rekening":"3001764577","nama_bank":"BPD JAMBI...","cabang_kcp_unit":"BPD JAMBI CABANG MUARA BUNGO...","rekening_atas_nama":"DNBOSSDN200IIEMBACANGGEDANG...","mbs":1,"luas_tanah_milik":10000,"luas_tanah_bukan_milik":0,"kode_registrasi":"101717547951628","npwp":"001155928332000               ","nm_wp":null,"keaktifan":"1","flag":"3  ","daya_listrik":1300,"kontinuitas_listrik":"1","jarak_listrik":0,"wilayah_terpencil":"0","wilayah_perbatasan":"0","wilayah_transmigrasi":"0","wilayah_adat_terpencil":"0","wilayah_bencana_alam":"0","wilayah_bencana_sosial":"0","partisipasi_bos":"1","waktu_penyelenggaraan_id":1,"waktu_penyelenggaraan":"Pagi/6 hari","sumber_listrik_id":2,"sumber_listrik":"PLN","sertifikasi_iso_id":9,"sertifikasi_iso":"Belum Bersertifikat","akses_internet_id":2,"akses_internet":"Telkom Speedy","akses_internet_2_id":2,"akses_internet_2":"Telkom Speedy","akreditasi":"B","create_date":"2018-01-24T12:09:39.813000","last_update":"2022-03-10T11:08:09.470000"},{"sekolah_id":"4007825c-0c26-e111-bd59-cf4d5ec9159b","semester_id":"20222","nama":"SD NEGERI 052II TEBING TINGGI","nama_nomenklatur":null,"nss":"101100204052","npsn":"10500637","bentuk_pendidikan_id":5,"bentuk_pendidikan":"SD","alamat_jalan":"Tebing Tinggi","rt":0,"rw":0,"nama_dusun":"TEBING TINGGI","kode_wilayah":"100299AG","kode_desa_kelurahan":"100299AG","desa_kelurahan":"TEBING TINGGI","kode_kecamatan":"100299  ","kecamatan":"Kec. Tanah Sepenggal Lintas","kode_kabupaten":"100200  ","kabupaten":"Kab. Bungo","kode_provinsi":"100000  ","provinsi":"Prov. Jambi","kode_pos":"37263","lintang":-1.3988,"bujur":101.9286,"nomor_telepon":"081349338348","nomor_fax":"0","email":"sd_tebing.tinggi@yahoo.com","website":"http://","kebutuhan_khusus_id":0,"kebutuhan_khusus":"Tidak ada","status_sekolah_id":"1","status_sekolah":"NEGERI","sk_pendirian_sekolah":"0","tanggal_sk_pendirian":"1910-01-01","status_kepemilikan_id":1,"status_kepemilikan":"Pemerintah Pusat","yayasan_id":null,"yayasan":null,"sk_izin_operasional":"-","tanggal_sk_izin_operasional":"1910-01-01","no_rekening":"3720055648","nama_bank":"GIRO POS","cabang_kcp_unit":"Muara Bungo","rekening_atas_nama":"SDN 52/II TEBING TINGGI","mbs":0,"luas_tanah_milik":4176,"luas_tanah_bukan_milik":0,"kode_registrasi":"101713537148428","npwp":"001155928332000               ","nm_wp":"SDN 52/II Tebing Tinggi","keaktifan":"1","flag":null,"daya_listrik":900,"kontinuitas_listrik":"1","jarak_listrik":0,"wilayah_terpencil":"0","wilayah_perbatasan":"0","wilayah_transmigrasi":"0","wilayah_adat_terpencil":"0","wilayah_bencana_alam":"0","wilayah_bencana_sosial":"0","partisipasi_bos":"1","waktu_penyelenggaraan_id":1,"waktu_penyelenggaraan":"Pagi/6 hari","sumber_listrik_id":2,"sumber_listrik":"PLN","sertifikasi_iso_id":9,"sertifikasi_iso":"Belum Bersertifikat","akses_internet_id":4,"akses_internet":"Telkomsel Flash","akses_internet_2_id":2,"akses_internet_2":"Telkom Speedy","akreditasi":"C","create_date":"2018-01-24T12:09:39.813000","last_update":"2022-03-10T11:08:09.470000"},{"sekolah_id":"ba06253f-9ab1-428f-9c67-c1721e444889","semester_id":"20222","nama":"KB KASIH BUNDA","nama_nomenklatur":null,"nss":"****        ","npsn":"69886811","bentuk_pendidikan_id":2,"bentuk_pendidikan":"KB","alamat_jalan":"DUSUN TEBING TINGGI","rt":5,"rw":null,"nama_dusun":"TEBING TINGGI","kode_wilayah":"100299AG","kode_desa_kelurahan":"100299AG","desa_kelurahan":"TEBING TINGGI","kode_kecamatan":"100299  ","kecamatan":"Kec. Tanah Sepenggal Lintas","kode_kabupaten":"100200  ","kabupaten":"Kab. Bungo","kode_provinsi":"100000  ","provinsi":"Prov. Jambi","kode_pos":"37263","lintang":0.0,"bujur":0.0,"nomor_telepon":"081366515210","nomor_fax":null,"email":"kbkasihbundatt@gmail.com","website":"http://","kebutuhan_khusus_id":0,"kebutuhan_khusus":"Tidak ada","status_sekolah_id":"2","status_sekolah":"SWASTA","sk_pendirian_sekolah":null,"tanggal_sk_pendirian":null,"status_kepemilikan_id":4,"status_kepemilikan":"Lainnya","yayasan_id":"ab70d553-4890-4ead-82f6-05e1ee2a9df7","yayasan":"PAUD KASIH BUNDA","sk_izin_operasional":"10 TAHUN 2014","tanggal_sk_izin_operasional":null,"no_rekening":"3004193031","nama_bank":"BPD JAMBI","cabang_kcp_unit":"Cabang Ma Bungo","rekening_atas_nama":"69886811 PAUD KASIH BUNDA","mbs":0,"luas_tanah_milik":0,"luas_tanah_bukan_milik":330,"kode_registrasi":"69428259238298","npwp":"808421986332000               ","nm_wp":"PAUD KASIH BUNDA","keaktifan":"1","flag":null,"daya_listrik":13,"kontinuitas_listrik":"1","jarak_listrik":0,"wilayah_terpencil":"0","wilayah_perbatasan":"0","wilayah_transmigrasi":"0","wilayah_adat_terpencil":"0","wilayah_bencana_alam":"0","wilayah_bencana_sosial":"0","partisipasi_bos":"1","waktu_penyelenggaraan_id":1,"waktu_penyelenggaraan":"Pagi/6 hari","sumber_listrik_id":2,"sumber_listrik":"PLN","sertifikasi_iso_id":9,"sertifikasi_iso":"Belum Bersertifikat","akses_internet_id":4,"akses_internet":"Telkomsel Flash","akses_internet_2_id":4,"akses_internet_2":"Telkomsel Flash","akreditasi":"C","create_date":"2018-02-06T22:59:03.437000","last_update":"2015-08-27T12:47:00"},{"sekolah_id":"0054915c-0c26-e111-97cf-358d86628c6c","semester_id":"20222","nama":"SD NEGERI 150II RANTAU EMBACANG","nama_nomenklatur":null,"nss":"101100215150","npsn":"10500608","bentuk_pendidikan_id":5,"bentuk_pendidikan":"SD","alamat_jalan":"Desa Rantau Embacang","rt":3,"rw":0,"nama_dusun":"Bukit Cermin","kode_wilayah":"100299AH","kode_desa_kelurahan":"100299AH","desa_kelurahan":"DESA RANTAU EMBACANG","kode_kecamatan":"100299  ","kecamatan":"Kec. Tanah Sepenggal Lintas","kode_kabupaten":"100200  ","kabupaten":"Kab. Bungo","kode_provinsi":"100000  ","provinsi":"Prov. Jambi","kode_pos":"37263","lintang":-1.3982,"bujur":101.9201,"nomor_telepon":"085274502330","nomor_fax":null,"email":"deswita_hndr@yahoo.com","website":"http://sdn150.com","kebutuhan_khusus_id":0,"kebutuhan_khusus":"Tidak ada","status_sekolah_id":"1","status_sekolah":"NEGERI","sk_pendirian_sekolah":"0","tanggal_sk_pendirian":"1977-03-01","status_kepemilikan_id":2,"status_kepemilikan":"Pemerintah Daerah","yayasan_id":null,"yayasan":null,"sk_izin_operasional":"-","tanggal_sk_izin_operasional":"1910-01-01","no_rekening":"3001765506","nama_bank":"BPD JAMBI...","cabang_kcp_unit":"BPD JAMBI CABANG MUARA BUNGO...","rekening_atas_nama":"DNBOSSDN150IIRANTAUEMBACANG...","mbs":0,"luas_tanah_milik":3375,"luas_tanah_bukan_milik":0,"kode_registrasi":"101779249309196","npwp":"001155928332000               ","nm_wp":"BEND. BOS. SD. NO. 150/II RANTAU EMBACANG","keaktifan":"1","flag":null,"daya_listrik":1300,"kontinuitas_listrik":"1","jarak_listrik":0,"wilayah_terpencil":"0","wilayah_perbatasan":"0","wilayah_transmigrasi":"0","wilayah_adat_terpencil":"0","wilayah_bencana_alam":"0","wilayah_bencana_sosial":"0","partisipasi_bos":"1","waktu_penyelenggaraan_id":1,"waktu_penyelenggaraan":"Pagi/6 hari","sumber_listrik_id":2,"sumber_listrik":"PLN","sertifikasi_iso_id":9,"sertifikasi_iso":"Belum Bersertifikat","akses_internet_id":4,"akses_internet":"Telkomsel Flash","akses_internet_2_id":0,"akses_internet_2":"Tidak Ada","akreditasi":"B","create_date":"2018-01-24T12:09:39.813000","last_update":"2022-03-10T11:08:09.470000"},{"sekolah_id":"cc99b502-6d4c-4a00-afe7-e94003821e39","semester_id":"20222","nama":"SMK KESEHATAN DHARMA ANANDA","nama_nomenklatur":null,"nss":"****        ","npsn":"69909110","bentuk_pendidikan_id":15,"bentuk_pendidikan":"SMK","alamat_jalan":"JL. M. TAHER EMBACANG GEDANG","rt":3,"rw":1,"nama_dusun":"Embacang Gedang","kode_wilayah":"100299AA","kode_desa_kelurahan":"100299AA","desa_kelurahan":"Embacang Gedang","kode_kecamatan":"100299  ","kecamatan":"Kec. Tanah Sepenggal Lintas","kode_kabupaten":"100200  ","kabupaten":"Kab. Bungo","kode_provinsi":"100000  ","provinsi":"Prov. Jambi","kode_pos":"37263","lintang":-1.4009,"bujur":102.022078,"nomor_telepon":"08127487204","nomor_fax":null,"email":"dharmaanandasmk@gmail.com","website":"http://","kebutuhan_khusus_id":0,"kebutuhan_khusus":"Tidak ada","status_sekolah_id":"2","status_sekolah":"SWASTA","sk_pendirian_sekolah":"68","tanggal_sk_pendirian":"2011-04-12","status_kepemilikan_id":3,"status_kepemilikan":"Yayasan","yayasan_id":"fa683a06-979f-4e94-9a20-4dd86ecd8f7a","yayasan":"Yayasan Pendidikan Darma Bakti Ananda","sk_izin_operasional":"194 TAHUN 2015","tanggal_sk_izin_operasional":"2015-07-06","no_rekening":"0705739870","nama_bank":"BNI","cabang_kcp_unit":"Muara Bungo","rekening_atas_nama":"SMK KESEHATAN DHARMA ANANDA","mbs":1,"luas_tanah_milik":1519,"luas_tanah_bukan_milik":0,"kode_registrasi":"2978992639085","npwp":"026939736332000               ","nm_wp":null,"keaktifan":"1","flag":null,"daya_listrik":1300,"kontinuitas_listrik":"1","jarak_listrik":0,"wilayah_terpencil":"0","wilayah_perbatasan":"0","wilayah_transmigrasi":"0","wilayah_adat_terpencil":"0","wilayah_bencana_alam":"0","wilayah_bencana_sosial":"0","partisipasi_bos":"1","waktu_penyelenggaraan_id":1,"waktu_penyelenggaraan":"Pagi/6 hari","sumber_listrik_id":2,"sumber_listrik":"PLN","sertifikasi_iso_id":9,"sertifikasi_iso":"Belum Bersertifikat","akses_internet_id":4,"akses_internet":"Telkomsel Flash","akses_internet_2_id":2,"akses_internet_2":"Telkom Speedy","akreditasi":"C","create_date":"2018-01-24T09:47:14.603000","last_update":"2022-03-10T11:08:09.470000"},{"sekolah_id":"efcc9804-6d78-41ba-9539-afa19f5b365d","semester_id":"20222","nama":"PKBM MIFTAHUL","nama_nomenklatur":null,"nss":"****        ","npsn":"P9934547","bentuk_pendidikan_id":27,"bentuk_pendidikan":"PKBM","alamat_jalan":"Desa Tanah Periuk","rt":0,"rw":0,"nama_dusun":"TANAH PERIUK","kode_wilayah":"100299AB","kode_desa_kelurahan":"100299AB","desa_kelurahan":"Tanah Periuk","kode_kecamatan":"100299  ","kecamatan":"Kec. Tanah Sepenggal Lintas","kode_kabupaten":"100200  ","kabupaten":"Kab. Bungo","kode_provinsi":"100000  ","provinsi":"Prov. Jambi","kode_pos":"37263","lintang":-1.391391,"bujur":101.967409,"nomor_telepon":"085369753969","nomor_fax":null,"email":"pkbmmiftahul@yahoo.com","website":"http://","kebutuhan_khusus_id":0,"kebutuhan_khusus":"Tidak ada","status_sekolah_id":"2","status_sekolah":"SWASTA","sk_pendirian_sekolah":"1","tanggal_sk_pendirian":"2007-06-04","status_kepemilikan_id":3,"status_kepemilikan":"Yayasan","yayasan_id":null,"yayasan":null,"sk_izin_operasional":"83 Tahun 2007","tanggal_sk_izin_operasional":"2007-05-28","no_rekening":"3004195239","nama_bank":"BPD JAMBI","cabang_kcp_unit":"CABANG MUARA BUNGO","rekening_atas_nama":"P9934547 PKBM MIFTAHUL","mbs":0,"luas_tanah_milik":0,"luas_tanah_bukan_milik":1000,"kode_registrasi":"5054319786093","npwp":"026096800332000               ","nm_wp":"YAYASAN PKBM MIFTAHUL","keaktifan":"1","flag":null,"daya_listrik":0,"kontinuitas_listrik":"1","jarak_listrik":0,"wilayah_terpencil":"0","wilayah_perbatasan":"0","wilayah_transmigrasi":"0","wilayah_adat_terpencil":"0","wilayah_bencana_alam":"0","wilayah_bencana_sosial":"0","partisipasi_bos":"1","waktu_penyelenggaraan_id":2,"waktu_penyelenggaraan":"Siang/6 hari","sumber_listrik_id":2,"sumber_listrik":"PLN","sertifikasi_iso_id":8,"sertifikasi_iso":"Proses Sertifikasi","akses_internet_id":4,"akses_internet":"Telkomsel Flash","akses_internet_2_id":4,"akses_internet_2":"Telkomsel Flash","akreditasi":"B","create_date":"2018-02-06T22:59:03.437000","last_update":"2022-03-10T11:08:09.470000"},{"sekolah_id":"0656feb9-dd53-45d4-bf64-d5d7880db26c","semester_id":"20222","nama":"KB PERMATA BIRU MAKMUR","nama_nomenklatur":null,"nss":"****        ","npsn":"69924226","bentuk_pendidikan_id":2,"bentuk_pendidikan":"KB","alamat_jalan":"Dusun Rantau Makmur","rt":1,"rw":null,"nama_dusun":"Laman Pajang","kode_wilayah":"100299AL","kode_desa_kelurahan":"100299AL","desa_kelurahan":"RANTAU MAKMUR","kode_kecamatan":"100299  ","kecamatan":"Kec. Tanah Sepenggal Lintas","kode_kabupaten":"100200  ","kabupaten":"Kab. Bungo","kode_provinsi":"100000  ","provinsi":"Prov. Jambi","kode_pos":"37263","lintang":-1.380968,"bujur":101.909008,"nomor_telepon":"082176341169","nomor_fax":null,"email":"paud_pbiru@yahoo.co.id","website":"http://","kebutuhan_khusus_id":0,"kebutuhan_khusus":"Tidak ada","status_sekolah_id":"2","status_sekolah":"SWASTA","sk_pendirian_sekolah":"22","tanggal_sk_pendirian":"2015-12-08","status_kepemilikan_id":4,"status_kepemilikan":"Lainnya","yayasan_id":"a6b1ea34-adf2-42a4-8399-29ca25535ace","yayasan":"PAUD PERMATA BIRU","sk_izin_operasional":"197 tahun 2015","tanggal_sk_izin_operasional":"2015-09-30","no_rekening":"3004194607","nama_bank":"BPD JAMBI","cabang_kcp_unit":"Cabang Ma Bungo","rekening_atas_nama":"69924226 KB PERMATA BIRU MAKMUR","mbs":0,"luas_tanah_milik":150,"luas_tanah_bukan_milik":0,"kode_registrasi":"204502016087005","npwp":"747515252332000               ","nm_wp":"PAUD PERMATA BIRU","keaktifan":"1","flag":null,"daya_listrik":1300,"kontinuitas_listrik":"1","jarak_listrik":0,"wilayah_terpencil":"0","wilayah_perbatasan":"0","wilayah_transmigrasi":"0","wilayah_adat_terpencil":"0","wilayah_bencana_alam":"0","wilayah_bencana_sosial":"0","partisipasi_bos":"1","waktu_penyelenggaraan_id":1,"waktu_penyelenggaraan":"Pagi/6 hari","sumber_listrik_id":2,"sumber_listrik":"PLN","sertifikasi_iso_id":9,"sertifikasi_iso":"Belum Bersertifikat","akses_internet_id":0,"akses_internet":"Tidak Ada","akses_internet_2_id":0,"akses_internet_2":"Tidak Ada","akreditasi":"C","create_date":"2018-02-06T22:59:03.437000","last_update":"2022-03-10T11:08:09.470000"},{"sekolah_id":"222da9a6-47ea-49f4-99c5-a82a7a5e685f","semester_id":"20222","nama":"SMAN 7 BUNGO","nama_nomenklatur":null,"nss":"301100204007","npsn":"10500692","bentuk_pendidikan_id":13,"bentuk_pendidikan":"SMA","alamat_jalan":"JL. DESA LUBUK LANDAI","rt":0,"rw":0,"nama_dusun":"LUBUK LANDAI","kode_wilayah":"100299AE","kode_desa_kelurahan":"100299AE","desa_kelurahan":"Lubuk Landai","kode_kecamatan":"100299  ","kecamatan":"Kec. Tanah Sepenggal Lintas","kode_kabupaten":"100200  ","kabupaten":"Kab. Bungo","kode_provinsi":"100000  ","provinsi":"Prov. Jambi","kode_pos":"37263","lintang":-1.4025,"bujur":101.9529,"nomor_telepon":"7325007","nomor_fax":null,"email":"smansataseplin@gmail.com","website":"http://smansataseplin.co.id","kebutuhan_khusus_id":0,"kebutuhan_khusus":"Tidak ada","status_sekolah_id":"1","status_sekolah":"NEGERI","sk_pendirian_sekolah":"0313 0 1995","tanggal_sk_pendirian":"2019-03-12","status_kepemilikan_id":2,"status_kepemilikan":"Pemerintah Daerah","yayasan_id":null,"yayasan":null,"sk_izin_operasional":"S.838/DISDIK-1.1/III/2019","tanggal_sk_izin_operasional":"2019-03-12","no_rekening":"0296178133","nama_bank":"BNI","cabang_kcp_unit":"Muara Bungo","rekening_atas_nama":"SMAN 1 TANAH SEPENGGAL","mbs":1,"luas_tanah_milik":11800,"luas_tanah_bukan_milik":0,"kode_registrasi":"5356287656974","npwp":"825162761332000               ","nm_wp":null,"keaktifan":"1","flag":"3  ","daya_listrik":3500,"kontinuitas_listrik":"1","jarak_listrik":0,"wilayah_terpencil":"0","wilayah_perbatasan":"0","wilayah_transmigrasi":"0","wilayah_adat_terpencil":"0","wilayah_bencana_alam":"0","wilayah_bencana_sosial":"0","partisipasi_bos":"1","waktu_penyelenggaraan_id":1,"waktu_penyelenggaraan":"Pagi/6 hari","sumber_listrik_id":2,"sumber_listrik":"PLN","sertifikasi_iso_id":9,"sertifikasi_iso":"Belum Bersertifikat","akses_internet_id":0,"akses_internet":"Tidak Ada","akses_internet_2_id":94,"akses_internet_2":"Lainnya (Satelit)","akreditasi":"A","create_date":"2018-01-24T09:47:14.603000","last_update":"2022-05-30T12:56:38.040000"},{"sekolah_id":"b03db461-0c26-e111-9718-191917300102","semester_id":"20222","nama":"SMP NEGERI 04 TANAH SEPENGGAL","nama_nomenklatur":null,"nss":"201100231025","npsn":"10500721","bentuk_pendidikan_id":6,"bentuk_pendidikan":"SMP","alamat_jalan":"Desa Tanah Periuk","rt":0,"rw":0,"nama_dusun":"Tanah Periuk","kode_wilayah":"100299AB","kode_desa_kelurahan":"100299AB","desa_kelurahan":"Tanah Periuk","kode_kecamatan":"100299  ","kecamatan":"Kec. Tanah Sepenggal Lintas","kode_kabupaten":"100200  ","kabupaten":"Kab. Bungo","kode_provinsi":"100000  ","provinsi":"Prov. Jambi","kode_pos":"37263","lintang":-1.397,"bujur":101.9651,"nomor_telepon":"082281156880","nomor_fax":null,"email":"riskyintanerlita25@gmail.com","website":"http://","kebutuhan_khusus_id":0,"kebutuhan_khusus":"Tidak ada","status_sekolah_id":"1","status_sekolah":"NEGERI","sk_pendirian_sekolah":"0283/0/1991","tanggal_sk_pendirian":"1991-01-01","status_kepemilikan_id":2,"status_kepemilikan":"Pemerintah Daerah","yayasan_id":null,"yayasan":null,"sk_izin_operasional":"-","tanggal_sk_izin_operasional":"1910-01-01","no_rekening":"3002419342","nama_bank":"BPD JAMBI...","cabang_kcp_unit":"BPD JAMBI CABANG  BUNGO...","rekening_atas_nama":"DNBOSSMPN4TANAHSEPENGGAL...","mbs":1,"luas_tanah_milik":18200,"luas_tanah_bukan_milik":0,"kode_registrasi":"107426756961804","npwp":"001155928332000               ","nm_wp":"SMP 4 Tanah Sepenggal","keaktifan":"1","flag":"3  ","daya_listrik":1300,"kontinuitas_listrik":"1","jarak_listrik":0,"wilayah_terpencil":"0","wilayah_perbatasan":"0","wilayah_transmigrasi":"0","wilayah_adat_terpencil":"0","wilayah_bencana_alam":"0","wilayah_bencana_sosial":"0","partisipasi_bos":"1","waktu_penyelenggaraan_id":1,"waktu_penyelenggaraan":"Pagi/6 hari","sumber_listrik_id":2,"sumber_listrik":"PLN","sertifikasi_iso_id":9,"sertifikasi_iso":"Belum Bersertifikat","akses_internet_id":2,"akses_internet":"Telkom Speedy","akses_internet_2_id":2,"akses_internet_2":"Telkom Speedy","akreditasi":"B","create_date":"2018-01-24T12:09:39.813000","last_update":"2023-05-31T20:35:39.977000"},{"sekolah_id":"e51911dc-cb1b-45cc-b255-6739899e2d3a","semester_id":"20222","nama":"KB DAMBAAN HATI","nama_nomenklatur":null,"nss":"****        ","npsn":"69934457","bentuk_pendidikan_id":2,"bentuk_pendidikan":"KB","alamat_jalan":"dusun sungai puri","rt":null,"rw":null,"nama_dusun":"SUNGAI PURI","kode_wilayah":"100299AJ","kode_desa_kelurahan":"100299AJ","desa_kelurahan":"Sungai Puri","kode_kecamatan":"100299  ","kecamatan":"Kec. Tanah Sepenggal Lintas","kode_kabupaten":"100200  ","kabupaten":"Kab. Bungo","kode_provinsi":"100000  ","provinsi":"Prov. Jambi","kode_pos":"37263","lintang":-1.40968,"bujur":101.903869,"nomor_telepon":null,"nomor_fax":null,"email":"paud.dambaanhati@gmail.com","website":"http://","kebutuhan_khusus_id":0,"kebutuhan_khusus":"Tidak ada","status_sekolah_id":"2","status_sekolah":"SWASTA","sk_pendirian_sekolah":"06","tanggal_sk_pendirian":"2009-10-14","status_kepemilikan_id":3,"status_kepemilikan":"Yayasan","yayasan_id":"90668d0b-ac68-4ee7-b991-5cc46a0f05aa","yayasan":"DAMBAAN HATI","sk_izin_operasional":"09 tahun 2015","tanggal_sk_izin_operasional":"2015-01-06","no_rekening":"3004194585","nama_bank":"BPD JAMBI","cabang_kcp_unit":"Cabang Ma Bungo","rekening_atas_nama":"69934457 KB.DAMBAAN HATI","mbs":0,"luas_tanah_milik":900,"luas_tanah_bukan_milik":0,"kode_registrasi":"241966007000011","npwp":"751053679332000               ","nm_wp":null,"keaktifan":"1","flag":null,"daya_listrik":900,"kontinuitas_listrik":"1","jarak_listrik":0,"wilayah_terpencil":"0","wilayah_perbatasan":"0","wilayah_transmigrasi":"0","wilayah_adat_terpencil":"0","wilayah_bencana_alam":"0","wilayah_bencana_sosial":"0","partisipasi_bos":"1","waktu_penyelenggaraan_id":1,"waktu_penyelenggaraan":"Pagi/6 hari","sumber_listrik_id":2,"sumber_listrik":"PLN","sertifikasi_iso_id":9,"sertifikasi_iso":"Belum Bersertifikat","akses_internet_id":4,"akses_internet":"Telkomsel Flash","akses_internet_2_id":4,"akses_internet_2":"Telkomsel Flash","akreditasi":"B","create_date":"2018-02-06T22:59:03.437000","last_update":"2022-03-10T11:08:09.470000"},{"sekolah_id":"2067825c-0c26-e111-ab1e-bbe79a0b77c4","semester_id":"20222","nama":"SD NEGERI 117 II Lubuk Landai","nama_nomenklatur":null,"nss":"101100204117","npsn":"10500575","bentuk_pendidikan_id":5,"bentuk_pendidikan":"SD","alamat_jalan":"Lubuk Landai","rt":0,"rw":0,"nama_dusun":"Lubuk Landai","kode_wilayah":"100299AE","kode_desa_kelurahan":"100299AE","desa_kelurahan":"Lubuk Landai","kode_kecamatan":"100299  ","kecamatan":"Kec. Tanah Sepenggal Lintas","kode_kabupaten":"100200  ","kabupaten":"Kab. Bungo","kode_provinsi":"100000  ","provinsi":"Prov. Jambi","kode_pos":"37263","lintang":-1.3963,"bujur":101.9491,"nomor_telepon":"085266979966","nomor_fax":null,"email":"is.reval@yahoo.com","website":"http://localhost:5774/","kebutuhan_khusus_id":0,"kebutuhan_khusus":"Tidak ada","status_sekolah_id":"1","status_sekolah":"NEGERI","sk_pendirian_sekolah":"01/01/1975","tanggal_sk_pendirian":"1975-01-01","status_kepemilikan_id":1,"status_kepemilikan":"Pemerintah Pusat","yayasan_id":null,"yayasan":null,"sk_izin_operasional":"-","tanggal_sk_izin_operasional":"1910-01-01","no_rekening":"0204026521","nama_bank":"BPD JAMBI","cabang_kcp_unit":"cabang","rekening_atas_nama":"SD","mbs":1,"luas_tanah_milik":60000,"luas_tanah_bukan_milik":0,"kode_registrasi":"101715145664012","npwp":"001155928332000               ","nm_wp":null,"keaktifan":"1","flag":"3  ","daya_listrik":1300,"kontinuitas_listrik":"1","jarak_listrik":0,"wilayah_terpencil":"0","wilayah_perbatasan":"0","wilayah_transmigrasi":"0","wilayah_adat_terpencil":"0","wilayah_bencana_alam":"0","wilayah_bencana_sosial":"0","partisipasi_bos":"1","waktu_penyelenggaraan_id":1,"waktu_penyelenggaraan":"Pagi/6 hari","sumber_listrik_id":2,"sumber_listrik":"PLN","sertifikasi_iso_id":9,"sertifikasi_iso":"Belum Bersertifikat","akses_internet_id":2,"akses_internet":"Telkom Speedy","akses_internet_2_id":19,"akses_internet_2":"Linknet","akreditasi":"B","create_date":"2018-01-24T12:09:39.813000","last_update":"2022-03-10T11:08:09.470000"},{"sekolah_id":"baaf358f-b685-4367-b106-cbc121404c60","semester_id":"20222","nama":"KB AL-AMIN","nama_nomenklatur":null,"nss":"****        ","npsn":"69791914","bentuk_pendidikan_id":2,"bentuk_pendidikan":"KB","alamat_jalan":"SUNGAI LIMAU","rt":null,"rw":null,"nama_dusun":"tanah periuk","kode_wilayah":"100299AB","kode_desa_kelurahan":"100299AB","desa_kelurahan":"Tanah Periuk","kode_kecamatan":"100299  ","kecamatan":"Kec. Tanah Sepenggal Lintas","kode_kabupaten":"100200  ","kabupaten":"Kab. Bungo","kode_provinsi":"100000  ","provinsi":"Prov. Jambi","kode_pos":null,"lintang":0.0,"bujur":0.0,"nomor_telepon":null,"nomor_fax":null,"email":null,"website":"http://","kebutuhan_khusus_id":0,"kebutuhan_khusus":"Tidak ada","status_sekolah_id":"2","status_sekolah":"SWASTA","sk_pendirian_sekolah":"NOMOR 145 2012","tanggal_sk_pendirian":"2012-08-06","status_kepemilikan_id":4,"status_kepemilikan":"Lainnya","yayasan_id":"93fbc2bd-f900-4649-b709-7cfe66e3be5b","yayasan":"paud al amin","sk_izin_operasional":"NOMOR 503 090 PNF DPMPTSP 2023","tanggal_sk_izin_operasional":"2016-03-01","no_rekening":"3004192884","nama_bank":"BPD JAMBI","cabang_kcp_unit":"Cabang Ma Bungo","rekening_atas_nama":"69791914 KB AL AMIN","mbs":0,"luas_tanah_milik":0,"luas_tanah_bukan_milik":400,"kode_registrasi":"157460744275382","npwp":"028754570332000               ","nm_wp":"paud al al amin","keaktifan":"1","flag":null,"daya_listrik":900,"kontinuitas_listrik":"1","jarak_listrik":0,"wilayah_terpencil":"0","wilayah_perbatasan":"0","wilayah_transmigrasi":"0","wilayah_adat_terpencil":"0","wilayah_bencana_alam":"0","wilayah_bencana_sosial":"0","partisipasi_bos":"1","waktu_penyelenggaraan_id":1,"waktu_penyelenggaraan":"Pagi/6 hari","sumber_listrik_id":2,"sumber_listrik":"PLN","sertifikasi_iso_id":9,"sertifikasi_iso":"Belum Bersertifikat","akses_internet_id":0,"akses_internet":"Tidak Ada","akses_internet_2_id":4,"akses_internet_2":"Telkomsel Flash","akreditasi":"C","create_date":"2018-02-06T22:59:03.437000","last_update":"2023-02-16T04:41:10.963000"},{"sekolah_id":"a0b7935c-0c26-e111-bb9f-d3877af94703","semester_id":"20222","nama":"SD NEGERI 153II LUBUK LANDAI","nama_nomenklatur":null,"nss":"101100208802","npsn":"10500595","bentuk_pendidikan_id":5,"bentuk_pendidikan":"SD","alamat_jalan":"Jl. Pendidikan, Kp. Betung","rt":0,"rw":0,"nama_dusun":"Kp. Betung","kode_wilayah":"100299AE","kode_desa_kelurahan":"100299AE","desa_kelurahan":"Lubuk Landai","kode_kecamatan":"100299  ","kecamatan":"Kec. Tanah Sepenggal Lintas","kode_kabupaten":"100200  ","kabupaten":"Kab. Bungo","kode_provinsi":"100000  ","provinsi":"Prov. Jambi","kode_pos":"37263","lintang":-1.3993,"bujur":101.9426,"nomor_telepon":null,"nomor_fax":null,"email":"sdn153_lubuklandai@yahoo.co.id","website":"http://","kebutuhan_khusus_id":0,"kebutuhan_khusus":"Tidak ada","status_sekolah_id":"1","status_sekolah":"NEGERI","sk_pendirian_sekolah":"Tidak Ada","tanggal_sk_pendirian":"2001-01-01","status_kepemilikan_id":2,"status_kepemilikan":"Pemerintah Daerah","yayasan_id":null,"yayasan":null,"sk_izin_operasional":"TIDAK ADA","tanggal_sk_izin_operasional":"2001-07-01","no_rekening":"3001765538","nama_bank":"BPD JAMBI...","cabang_kcp_unit":"BPD JAMBI CABANG MUARA BUNGO...","rekening_atas_nama":"DNBOSSDN153IILUBUKLANDAI...","mbs":1,"luas_tanah_milik":3253,"luas_tanah_bukan_milik":0,"kode_registrasi":"101789510673932","npwp":"001155928332000               ","nm_wp":"SDN 153II Lubuk Landai","keaktifan":"1","flag":"3  ","daya_listrik":1300,"kontinuitas_listrik":"1","jarak_listrik":0,"wilayah_terpencil":"0","wilayah_perbatasan":"0","wilayah_transmigrasi":"0","wilayah_adat_terpencil":"0","wilayah_bencana_alam":"0","wilayah_bencana_sosial":"0","partisipasi_bos":"1","waktu_penyelenggaraan_id":1,"waktu_penyelenggaraan":"Pagi/6 hari","sumber_listrik_id":2,"sumber_listrik":"PLN","sertifikasi_iso_id":9,"sertifikasi_iso":"Belum Bersertifikat","akses_internet_id":4,"akses_internet":"Telkomsel Flash","akses_internet_2_id":4,"akses_internet_2":"Telkomsel Flash","akreditasi":"B","create_date":"2018-01-24T12:09:39.813000","last_update":"2022-03-10T11:08:09.470000"},{"sekolah_id":"07f5a494-0508-4e4a-aabb-7b0879fd8e08","semester_id":"20222","nama":"SPS BELIMBING","nama_nomenklatur":null,"nss":"****        ","npsn":"69973738","bentuk_pendidikan_id":4,"bentuk_pendidikan":"SPS","alamat_jalan":"Desa Embacang Gedang","rt":1,"rw":null,"nama_dusun":null,"kode_wilayah":"100299AA","kode_desa_kelurahan":"100299AA","desa_kelurahan":"Embacang Gedang","kode_kecamatan":"100299  ","kecamatan":"Kec. Tanah Sepenggal Lintas","kode_kabupaten":"100200  ","kabupaten":"Kab. Bungo","kode_provinsi":"100000  ","provinsi":"Prov. Jambi","kode_pos":null,"lintang":0.0,"bujur":0.0,"nomor_telepon":null,"nomor_fax":null,"email":null,"website":"http://","kebutuhan_khusus_id":0,"kebutuhan_khusus":"Tidak ada","status_sekolah_id":"2","status_sekolah":"SWASTA","sk_pendirian_sekolah":"246","tanggal_sk_pendirian":"2010-01-02","status_kepemilikan_id":4,"status_kepemilikan":"Lainnya","yayasan_id":"ff684ffa-13dd-4620-a1c9-6d9c48eab88b","yayasan":"TAMAN SISWA","sk_izin_operasional":"246 Tahun 2010","tanggal_sk_izin_operasional":"2010-01-02","no_rekening":"3004193128","nama_bank":"BPD JAMBI","cabang_kcp_unit":"Cabang Ma Bungo","rekening_atas_nama":"69973738 SPS Belimbing","mbs":0,"luas_tanah_milik":15,"luas_tanah_bukan_milik":0,"kode_registrasi":"163436206426117","npwp":"842439606332000               ","nm_wp":"SPS BELIMBING","keaktifan":"1","flag":null,"daya_listrik":450,"kontinuitas_listrik":"1","jarak_listrik":0,"wilayah_terpencil":"0","wilayah_perbatasan":"0","wilayah_transmigrasi":"0","wilayah_adat_terpencil":"0","wilayah_bencana_alam":"0","wilayah_bencana_sosial":"0","partisipasi_bos":"1","waktu_penyelenggaraan_id":1,"waktu_penyelenggaraan":"Pagi/6 hari","sumber_listrik_id":2,"sumber_listrik":"PLN","sertifikasi_iso_id":9,"sertifikasi_iso":"Belum Bersertifikat","akses_internet_id":0,"akses_internet":"Tidak Ada","akses_internet_2_id":0,"akses_internet_2":"Tidak Ada","akreditasi":null,"create_date":"2018-03-06T05:36:40.153000","last_update":"2022-03-10T11:08:09.470000"},{"sekolah_id":"8003af61-0c26-e111-bd30-c377f1c49ac3","semester_id":"20222","nama":"SMP NEGERI 7 TANAH SEPENGGAL","nama_nomenklatur":null,"nss":"201100204038","npsn":"10500714","bentuk_pendidikan_id":6,"bentuk_pendidikan":"SMP","alamat_jalan":"Desa Lubuk Landai","rt":0,"rw":0,"nama_dusun":"Lubuk Landai","kode_wilayah":"100299AE","kode_desa_kelurahan":"100299AE","desa_kelurahan":"Lubuk Landai","kode_kecamatan":"100299  ","kecamatan":"Kec. Tanah Sepenggal Lintas","kode_kabupaten":"100200  ","kabupaten":"Kab. Bungo","kode_provinsi":"100000  ","provinsi":"Prov. Jambi","kode_pos":"37263","lintang":-1.3983,"bujur":101.9443,"nomor_telepon":null,"nomor_fax":null,"email":"smpn7.tasep@gmail.com","website":"http://","kebutuhan_khusus_id":0,"kebutuhan_khusus":"Tidak ada","status_sekolah_id":"1","status_sekolah":"NEGERI","sk_pendirian_sekolah":"45/P DAN K/TAHUN 2007","tanggal_sk_pendirian":"2007-02-08","status_kepemilikan_id":2,"status_kepemilikan":"Pemerintah Daerah","yayasan_id":null,"yayasan":null,"sk_izin_operasional":"425/162/Dikbud/2023","tanggal_sk_izin_operasional":"2023-02-22","no_rekening":"3002419407","nama_bank":"BPD JAMBI...","cabang_kcp_unit":"BPD JAMBI CABANG MUARA BUNGO...","rekening_atas_nama":"DNBOSSMPN7TANAHSEPENGGAL...","mbs":1,"luas_tanah_milik":12269,"luas_tanah_bukan_milik":0,"kode_registrasi":"107404305901068","npwp":"001155928332000               ","nm_wp":"SMPN 7 TANAH sEPENGGAL","keaktifan":"1","flag":"3  ","daya_listrik":1300,"kontinuitas_listrik":"1","jarak_listrik":0,"wilayah_terpencil":"0","wilayah_perbatasan":"0","wilayah_transmigrasi":"0","wilayah_adat_terpencil":"0","wilayah_bencana_alam":"0","wilayah_bencana_sosial":"0","partisipasi_bos":"1","waktu_penyelenggaraan_id":1,"waktu_penyelenggaraan":"Pagi/6 hari","sumber_listrik_id":2,"sumber_listrik":"PLN","sertifikasi_iso_id":9,"sertifikasi_iso":"Belum Bersertifikat","akses_internet_id":4,"akses_internet":"Telkomsel Flash","akses_internet_2_id":4,"akses_internet_2":"Telkomsel Flash","akreditasi":"A","create_date":"2018-01-24T12:09:39.813000","last_update":"2023-03-03T07:04:46.007000"},{"sekolah_id":"46c890b3-6875-41df-9dbd-f86a6963f672","semester_id":"20222","nama":"KB YASNI AL-MUBAROK","nama_nomenklatur":null,"nss":"****        ","npsn":"69886813","bentuk_pendidikan_id":2,"bentuk_pendidikan":"KB","alamat_jalan":"DESA RANTAU EMBACABG","rt":4,"rw":null,"nama_dusun":"RANTAU EMBACANG","kode_wilayah":"100299AH","kode_desa_kelurahan":"100299AH","desa_kelurahan":"RANTAU EMBACANG","kode_kecamatan":"100299  ","kecamatan":"Kec. Tanah Sepenggal Lintas","kode_kabupaten":"100200  ","kabupaten":"Kab. Bungo","kode_provinsi":"100000  ","provinsi":"Prov. Jambi","kode_pos":"37263","lintang":-1.398078,"bujur":101.918752,"nomor_telepon":"085382295426","nomor_fax":null,"email":"nurmay888@yahoo.com","website":"http://","kebutuhan_khusus_id":0,"kebutuhan_khusus":"Tidak ada","status_sekolah_id":"2","status_sekolah":"SWASTA","sk_pendirian_sekolah":null,"tanggal_sk_pendirian":null,"status_kepemilikan_id":3,"status_kepemilikan":"Yayasan","yayasan_id":"99f06841-a6aa-4289-9a38-d17e8bd14990","yayasan":"PAUD YASNI AL MUBAROK","sk_izin_operasional":"49 TAHUN 2014","tanggal_sk_izin_operasional":null,"no_rekening":"3004192787","nama_bank":"BPD JAMBI","cabang_kcp_unit":"Cabang Ma Bungo","rekening_atas_nama":"69886813 KB YASNI AL MUBAROK","mbs":0,"luas_tanah_milik":396,"luas_tanah_bukan_milik":0,"kode_registrasi":"197434416723304","npwp":"723734299332000               ","nm_wp":null,"keaktifan":"1","flag":null,"daya_listrik":1300,"kontinuitas_listrik":"1","jarak_listrik":0,"wilayah_terpencil":"0","wilayah_perbatasan":"0","wilayah_transmigrasi":"0","wilayah_adat_terpencil":"0","wilayah_bencana_alam":"0","wilayah_bencana_sosial":"0","partisipasi_bos":"1","waktu_penyelenggaraan_id":1,"waktu_penyelenggaraan":"Pagi/6 hari","sumber_listrik_id":2,"sumber_listrik":"PLN","sertifikasi_iso_id":9,"sertifikasi_iso":"Belum Bersertifikat","akses_internet_id":4,"akses_internet":"Telkomsel Flash","akses_internet_2_id":4,"akses_internet_2":"Telkomsel Flash","akreditasi":null,"create_date":"2018-02-06T22:59:03.437000","last_update":"2019-05-07T11:00:00"},{"sekolah_id":"b308b383-f494-4dce-9068-54396f10d880","semester_id":"20222","nama":"KB KEMBOJA","nama_nomenklatur":null,"nss":"****        ","npsn":"69791908","bentuk_pendidikan_id":2,"bentuk_pendidikan":"KB","alamat_jalan":"SEI. MANCUR RT.8","rt":8,"rw":null,"nama_dusun":"sei.tembang","kode_wilayah":"100299AD","kode_desa_kelurahan":"100299AD","desa_kelurahan":"Sungai Mancur","kode_kecamatan":"100299  ","kecamatan":"Kec. Tanah Sepenggal Lintas","kode_kabupaten":"100200  ","kabupaten":"Kab. Bungo","kode_provinsi":"100000  ","provinsi":"Prov. Jambi","kode_pos":"37215","lintang":0.0,"bujur":0.0,"nomor_telepon":null,"nomor_fax":null,"email":null,"website":"http://","kebutuhan_khusus_id":0,"kebutuhan_khusus":"Tidak ada","status_sekolah_id":"2","status_sekolah":"SWASTA","sk_pendirian_sekolah":"06","tanggal_sk_pendirian":"2009-02-21","status_kepemilikan_id":4,"status_kepemilikan":"Lainnya","yayasan_id":"83307269-43ef-4c6f-a578-0ec033e5c9fa","yayasan":"KB KEMBOJA","sk_izin_operasional":"06 tahun 2009","tanggal_sk_izin_operasional":"2009-02-21","no_rekening":"3004192973","nama_bank":"BPD JAMBI","cabang_kcp_unit":"Cabang Ma Bungo","rekening_atas_nama":"69791908 KB KEMBOJA","mbs":0,"luas_tanah_milik":0,"luas_tanah_bukan_milik":396,"kode_registrasi":"144804968371444","npwp":"809410822332000               ","nm_wp":null,"keaktifan":"1","flag":null,"daya_listrik":1300,"kontinuitas_listrik":"1","jarak_listrik":0,"wilayah_terpencil":"0","wilayah_perbatasan":"0","wilayah_transmigrasi":"0","wilayah_adat_terpencil":"0","wilayah_bencana_alam":"0","wilayah_bencana_sosial":"0","partisipasi_bos":"1","waktu_penyelenggaraan_id":1,"waktu_penyelenggaraan":"Pagi/6 hari","sumber_listrik_id":2,"sumber_listrik":"PLN","sertifikasi_iso_id":9,"sertifikasi_iso":"Belum Bersertifikat","akses_internet_id":4,"akses_internet":"Telkomsel Flash","akses_internet_2_id":4,"akses_internet_2":"Telkomsel Flash","akreditasi":"C","create_date":"2018-02-06T22:59:03.437000","last_update":"2022-03-10T11:08:09.470000"},{"sekolah_id":"60a6045c-0c26-e111-a9de-b98aefe6c3a0","semester_id":"20222","nama":"SD NEGERI 022II PEMATANG PANJANG","nama_nomenklatur":null,"nss":"101100285000","npsn":"10500988","bentuk_pendidikan_id":5,"bentuk_pendidikan":"SD","alamat_jalan":"Desa Pematang Panjang","rt":0,"rw":0,"nama_dusun":"PEMATANG PANJANG","kode_wilayah":"100299AF","kode_desa_kelurahan":"100299AF","desa_kelurahan":"PEMATANG PANJANG","kode_kecamatan":"100299  ","kecamatan":"Kec. Tanah Sepenggal Lintas","kode_kabupaten":"100200  ","kabupaten":"Kab. Bungo","kode_provinsi":"100000  ","provinsi":"Prov. Jambi","kode_pos":"37263","lintang":-1.3622486,"bujur":101.913376,"nomor_telepon":"085266736870","nomor_fax":null,"email":"sdn22_pematanpanjang@yahoo.co.id","website":"http://","kebutuhan_khusus_id":0,"kebutuhan_khusus":"Tidak ada","status_sekolah_id":"1","status_sekolah":"NEGERI","sk_pendirian_sekolah":"0","tanggal_sk_pendirian":"1997-01-01","status_kepemilikan_id":1,"status_kepemilikan":"Pemerintah Pusat","yayasan_id":null,"yayasan":null,"sk_izin_operasional":"-","tanggal_sk_izin_operasional":"1910-01-01","no_rekening":"3720055580","nama_bank":"Pos Giro","cabang_kcp_unit":"Muara Bungo","rekening_atas_nama":"SDN 22II Pematang Panjang","mbs":1,"luas_tanah_milik":8000,"luas_tanah_bukan_milik":0,"kode_registrasi":"101175040943628","npwp":"001155928332000               ","nm_wp":null,"keaktifan":"1","flag":null,"daya_listrik":1300,"kontinuitas_listrik":"1","jarak_listrik":0,"wilayah_terpencil":"0","wilayah_perbatasan":"0","wilayah_transmigrasi":"0","wilayah_adat_terpencil":"0","wilayah_bencana_alam":"0","wilayah_bencana_sosial":"0","partisipasi_bos":"1","waktu_penyelenggaraan_id":1,"waktu_penyelenggaraan":"Pagi/6 hari","sumber_listrik_id":2,"sumber_listrik":"PLN","sertifikasi_iso_id":9,"sertifikasi_iso":"Belum Bersertifikat","akses_internet_id":4,"akses_internet":"Telkomsel Flash","akses_internet_2_id":4,"akses_internet_2":"Telkomsel Flash","akreditasi":"C","create_date":"2018-01-24T12:09:39.813000","last_update":"2022-03-10T11:08:09.470000"},{"sekolah_id":"40230d63-0c26-e111-8181-b110f78ee0d1","semester_id":"20222","nama":"SMP NEGERI 6 TANAH SEPENGGAL","nama_nomenklatur":null,"nss":"201100204033","npsn":"10500712","bentuk_pendidikan_id":6,"bentuk_pendidikan":"SMP","alamat_jalan":"Jl. Lintas Sumatera Km 18 Muara Bungo - Padang ","rt":5,"rw":0,"nama_dusun":"Embacang Gedang","kode_wilayah":"100299AA","kode_desa_kelurahan":"100299AA","desa_kelurahan":"Embacang Gedang","kode_kecamatan":"100299  ","kecamatan":"Kec. Tanah Sepenggal Lintas","kode_kabupaten":"100200  ","kabupaten":"Kab. Bungo","kode_provinsi":"100000  ","provinsi":"Prov. Jambi","kode_pos":"37260","lintang":-1.4029,"bujur":102.0212,"nomor_telepon":"085271204539","nomor_fax":null,"email":"smpn6tanahsepenggal@gmail.com","website":"http://","kebutuhan_khusus_id":0,"kebutuhan_khusus":"Tidak ada","status_sekolah_id":"1","status_sekolah":"NEGERI","sk_pendirian_sekolah":"23.530.2.06.03.2003","tanggal_sk_pendirian":"2003-01-01","status_kepemilikan_id":2,"status_kepemilikan":"Pemerintah Daerah","yayasan_id":null,"yayasan":null,"sk_izin_operasional":"23.530.2.06.03.2003","tanggal_sk_izin_operasional":"2003-09-15","no_rekening":"3002419447","nama_bank":"BPD JAMBI...","cabang_kcp_unit":"BPD JAMBI CABANG MUARA BUNGO...","rekening_atas_nama":"DNBOSSMPN6TANAHSEPENGGAL...","mbs":1,"luas_tanah_milik":16609,"luas_tanah_bukan_milik":0,"kode_registrasi":"108908077131276","npwp":"001155928332000               ","nm_wp":"SMPN 6 TANAH SEPENGGAL","keaktifan":"1","flag":null,"daya_listrik":1300,"kontinuitas_listrik":"1","jarak_listrik":0,"wilayah_terpencil":"0","wilayah_perbatasan":"0","wilayah_transmigrasi":"0","wilayah_adat_terpencil":"0","wilayah_bencana_alam":"0","wilayah_bencana_sosial":"0","partisipasi_bos":"1","waktu_penyelenggaraan_id":1,"waktu_penyelenggaraan":"Pagi/6 hari","sumber_listrik_id":2,"sumber_listrik":"PLN","sertifikasi_iso_id":9,"sertifikasi_iso":"Belum Bersertifikat","akses_internet_id":4,"akses_internet":"Telkomsel Flash","akses_internet_2_id":91,"akses_internet_2":"Lainnya (Kabel)","akreditasi":"B","create_date":"2018-01-24T12:09:39.813000","last_update":"2022-03-10T11:08:09.470000"},{"sekolah_id":"00138e5d-0c26-e111-b2a4-8bac1122ba8d","semester_id":"20222","nama":"SD NEGERI 028II TANAH PERIUK","nama_nomenklatur":null,"nss":"101100204028","npsn":"10500961","bentuk_pendidikan_id":5,"bentuk_pendidikan":"SD","alamat_jalan":"Tanah Periuk","rt":0,"rw":0,"nama_dusun":"Tanah Periuk","kode_wilayah":"100299AB","kode_desa_kelurahan":"100299AB","desa_kelurahan":"Tanah Periuk","kode_kecamatan":"100299  ","kecamatan":"Kec. Tanah Sepenggal Lintas","kode_kabupaten":"100200  ","kabupaten":"Kab. Bungo","kode_provinsi":"100000  ","provinsi":"Prov. Jambi","kode_pos":"37263","lintang":-1.4031,"bujur":101.9613,"nomor_telepon":"085268457212","nomor_fax":"0","email":"ssdn28tanahperiuk@gmail.com","website":"http://","kebutuhan_khusus_id":0,"kebutuhan_khusus":"Tidak ada","status_sekolah_id":"1","status_sekolah":"NEGERI","sk_pendirian_sekolah":"06.03.10.06.4.00001","tanggal_sk_pendirian":"1949-01-01","status_kepemilikan_id":1,"status_kepemilikan":"Pemerintah Pusat","yayasan_id":null,"yayasan":null,"sk_izin_operasional":"893","tanggal_sk_izin_operasional":"2001-01-01","no_rekening":"016001002717532","nama_bank":"BANK RAKYAT INDONESI","cabang_kcp_unit":"cabang","rekening_atas_nama":"SD NEGERI NO.28/II TANAH PERIUK","mbs":1,"luas_tanah_milik":7081,"luas_tanah_bukan_milik":0,"kode_registrasi":"102864785516044","npwp":"001155928332000               ","nm_wp":"SD NEGERI 28/II TANAH PERIUK","keaktifan":"1","flag":null,"daya_listrik":1300,"kontinuitas_listrik":"1","jarak_listrik":0,"wilayah_terpencil":"0","wilayah_perbatasan":"0","wilayah_transmigrasi":"0","wilayah_adat_terpencil":"0","wilayah_bencana_alam":"0","wilayah_bencana_sosial":"0","partisipasi_bos":"1","waktu_penyelenggaraan_id":1,"waktu_penyelenggaraan":"Pagi/6 hari","sumber_listrik_id":2,"sumber_listrik":"PLN","sertifikasi_iso_id":9,"sertifikasi_iso":"Belum Bersertifikat","akses_internet_id":2,"akses_internet":"Telkom Speedy","akses_internet_2_id":2,"akses_internet_2":"Telkom Speedy","akreditasi":"B","create_date":"2018-01-24T12:09:39.813000","last_update":"2023-06-08T11:18:20.520000"},{"sekolah_id":"e5331d68-a305-4e11-87d9-02c9cb52b03d","semester_id":"20222","nama":"SMAN 16 BUNGO","nama_nomenklatur":null,"nss":"301100204017","npsn":"10505294","bentuk_pendidikan_id":13,"bentuk_pendidikan":"SMA","alamat_jalan":"JL. DS. TANAH PERIUK","rt":0,"rw":0,"nama_dusun":"TANAH PERIUK","kode_wilayah":"100299AB","kode_desa_kelurahan":"100299AB","desa_kelurahan":"Tanah Periuk","kode_kecamatan":"100299  ","kecamatan":"Kec. Tanah Sepenggal Lintas","kode_kabupaten":"100200  ","kabupaten":"Kab. Bungo","kode_provinsi":"100000  ","provinsi":"Prov. Jambi","kode_pos":"37256","lintang":-1.3952,"bujur":101.9699,"nomor_telepon":"0","nomor_fax":"0","email":"sma2tasepbungo@gmail.com","website":"http://www.sma2tasepbungo.com","kebutuhan_khusus_id":0,"kebutuhan_khusus":"Tidak ada","status_sekolah_id":"1","status_sekolah":"NEGERI","sk_pendirian_sekolah":"583/P dan K Tahun 2008","tanggal_sk_pendirian":"2008-04-22","status_kepemilikan_id":2,"status_kepemilikan":"Pemerintah Daerah","yayasan_id":null,"yayasan":null,"sk_izin_operasional":"583/P dan K Tahun 2008","tanggal_sk_izin_operasional":"2008-04-22","no_rekening":"016001003557309","nama_bank":"BRI...","cabang_kcp_unit":"BANK RAKYAT INDONESIA CABANG MUARA BUNGO...","rekening_atas_nama":"SMAN2TANAHSEPENGGAL...","mbs":1,"luas_tanah_milik":15693,"luas_tanah_bukan_milik":0,"kode_registrasi":"36240657194482","npwp":"822087615332000               ","nm_wp":"SMAN 2 TANAH SEPENGGAL","keaktifan":"1","flag":"3  ","daya_listrik":1300,"kontinuitas_listrik":"1","jarak_listrik":0,"wilayah_terpencil":"0","wilayah_perbatasan":"0","wilayah_transmigrasi":"0","wilayah_adat_terpencil":"0","wilayah_bencana_alam":"0","wilayah_bencana_sosial":"0","partisipasi_bos":"1","waktu_penyelenggaraan_id":1,"waktu_penyelenggaraan":"Pagi/6 hari","sumber_listrik_id":2,"sumber_listrik":"PLN","sertifikasi_iso_id":9,"sertifikasi_iso":"Belum Bersertifikat","akses_internet_id":4,"akses_internet":"Telkomsel Flash","akses_internet_2_id":91,"akses_internet_2":"Lainnya (Kabel)","akreditasi":"A","create_date":"2018-01-24T09:47:14.603000","last_update":"2022-03-10T11:08:09.470000"},{"sekolah_id":"0a736ff4-e958-4bc6-af61-93eaee6e0261","semester_id":"20222","nama":"KB PELITA HATI","nama_nomenklatur":null,"nss":"****        ","npsn":"69886810","bentuk_pendidikan_id":2,"bentuk_pendidikan":"KB","alamat_jalan":"POROS SUMBERJAYA","rt":null,"rw":null,"nama_dusun":null,"kode_wilayah":"100299AF","kode_desa_kelurahan":"100299AF","desa_kelurahan":"PEMATANG PANJANG","kode_kecamatan":"100299  ","kecamatan":"Kec. Tanah Sepenggal Lintas","kode_kabupaten":"100200  ","kabupaten":"Kab. Bungo","kode_provinsi":"100000  ","provinsi":"Prov. Jambi","kode_pos":null,"lintang":0.0,"bujur":0.0,"nomor_telepon":null,"nomor_fax":null,"email":null,"website":"http://","kebutuhan_khusus_id":0,"kebutuhan_khusus":"Tidak ada","status_sekolah_id":"2","status_sekolah":"SWASTA","sk_pendirian_sekolah":null,"tanggal_sk_pendirian":null,"status_kepemilikan_id":4,"status_kepemilikan":"Lainnya","yayasan_id":"9e8c31ee-f4ec-4c77-80a4-62943d7b133b","yayasan":"KB PELITA HATI","sk_izin_operasional":"119 TAHUN 2011","tanggal_sk_izin_operasional":null,"no_rekening":"3004194558","nama_bank":"BPD JAMBI","cabang_kcp_unit":"Cabang Ma Bungo","rekening_atas_nama":"69886810 KB PELITA HATI","mbs":0,"luas_tanah_milik":100,"luas_tanah_bukan_milik":0,"kode_registrasi":"268759508605161","npwp":"028755262332000               ","nm_wp":null,"keaktifan":"1","flag":null,"daya_listrik":1300,"kontinuitas_listrik":"1","jarak_listrik":0,"wilayah_terpencil":"0","wilayah_perbatasan":"0","wilayah_transmigrasi":"0","wilayah_adat_terpencil":"0","wilayah_bencana_alam":"0","wilayah_bencana_sosial":"0","partisipasi_bos":"1","waktu_penyelenggaraan_id":1,"waktu_penyelenggaraan":"Pagi/6 hari","sumber_listrik_id":2,"sumber_listrik":"PLN","sertifikasi_iso_id":9,"sertifikasi_iso":"Belum Bersertifikat","akses_internet_id":4,"akses_internet":"Telkomsel Flash","akses_internet_2_id":4,"akses_internet_2":"Telkomsel Flash","akreditasi":"C","create_date":"2018-02-06T22:59:03.437000","last_update":"2022-03-10T11:08:09.470000"},{"sekolah_id":"f0e8735c-0c26-e111-ac32-497bb0cbcc38","semester_id":"20222","nama":"SD NEGERI 051II PAKU AJI","nama_nomenklatur":null,"nss":"101100203051","npsn":"10500636","bentuk_pendidikan_id":5,"bentuk_pendidikan":"SD","alamat_jalan":"Desa Paku Aji","rt":0,"rw":0,"nama_dusun":"Paku Aji","kode_wilayah":"100299AI","kode_desa_kelurahan":"100299AI","desa_kelurahan":"Paku Aji","kode_kecamatan":"100299  ","kecamatan":"Kec. Tanah Sepenggal Lintas","kode_kabupaten":"100200  ","kabupaten":"Kab. Bungo","kode_provinsi":"100000  ","provinsi":"Prov. Jambi","kode_pos":"37263","lintang":-1.4025,"bujur":101.9084,"nomor_telepon":"085266925250","nomor_fax":null,"email":"sdn51.pakuajiI@yahoo.com","website":"http://","kebutuhan_khusus_id":0,"kebutuhan_khusus":"Tidak ada","status_sekolah_id":"1","status_sekolah":"NEGERI","sk_pendirian_sekolah":"893 TAHUN 2001","tanggal_sk_pendirian":"1910-01-01","status_kepemilikan_id":1,"status_kepemilikan":"Pemerintah Pusat","yayasan_id":null,"yayasan":null,"sk_izin_operasional":"893 TAHUN 2001","tanggal_sk_izin_operasional":"1910-01-01","no_rekening":"0204026696","nama_bank":"Bank 9 Jambi","cabang_kcp_unit":"BUNGO","rekening_atas_nama":"SDN 51/II PAKU AJI","mbs":1,"luas_tanah_milik":5162,"luas_tanah_bukan_milik":0,"kode_registrasi":"216775333374315","npwp":"001155928332000               ","nm_wp":null,"keaktifan":"1","flag":null,"daya_listrik":900,"kontinuitas_listrik":"1","jarak_listrik":0,"wilayah_terpencil":"0","wilayah_perbatasan":"0","wilayah_transmigrasi":"0","wilayah_adat_terpencil":"0","wilayah_bencana_alam":"0","wilayah_bencana_sosial":"0","partisipasi_bos":"1","waktu_penyelenggaraan_id":1,"waktu_penyelenggaraan":"Pagi/6 hari","sumber_listrik_id":2,"sumber_listrik":"PLN","sertifikasi_iso_id":9,"sertifikasi_iso":"Belum Bersertifikat","akses_internet_id":0,"akses_internet":"Tidak Ada","akses_internet_2_id":0,"akses_internet_2":"Tidak Ada","akreditasi":"C","create_date":"2018-01-24T12:09:39.813000","last_update":"2022-09-02T02:44:59.180000"},{"sekolah_id":"c4d95c6d-25d2-4fd6-8d5b-9905bee0b348","semester_id":"20222","nama":"KB AL-MUTTAQIN","nama_nomenklatur":null,"nss":"****        ","npsn":"69886808","bentuk_pendidikan_id":2,"bentuk_pendidikan":"KB","alamat_jalan":"SUNGAI TERUS","rt":1,"rw":1,"nama_dusun":"TANAH PERIUK","kode_wilayah":"100299AB","kode_desa_kelurahan":"100299AB","desa_kelurahan":"TANAH PERIUK","kode_kecamatan":"100299  ","kecamatan":"Kec. Tanah Sepenggal Lintas","kode_kabupaten":"100200  ","kabupaten":"Kab. Bungo","kode_provinsi":"100000  ","provinsi":"Prov. Jambi","kode_pos":"37263","lintang":0.0,"bujur":0.0,"nomor_telepon":"085357611619","nomor_fax":null,"email":"kbalmutaqintnperiuk@gmail.com","website":"http://","kebutuhan_khusus_id":0,"kebutuhan_khusus":"Tidak ada","status_sekolah_id":"2","status_sekolah":"SWASTA","sk_pendirian_sekolah":null,"tanggal_sk_pendirian":null,"status_kepemilikan_id":3,"status_kepemilikan":"Yayasan","yayasan_id":null,"yayasan":null,"sk_izin_operasional":"18","tanggal_sk_izin_operasional":null,"no_rekening":"3004192768","nama_bank":"BPD JAMBI","cabang_kcp_unit":"Cabang Ma Bungo","rekening_atas_nama":"69886808 KB AL MUTTAQIN","mbs":0,"luas_tanah_milik":81,"luas_tanah_bukan_milik":0,"kode_registrasi":"120245557973541","npwp":"669121840332000               ","nm_wp":null,"keaktifan":"1","flag":null,"daya_listrik":900,"kontinuitas_listrik":"1","jarak_listrik":0,"wilayah_terpencil":"0","wilayah_perbatasan":"0","wilayah_transmigrasi":"0","wilayah_adat_terpencil":"0","wilayah_bencana_alam":"0","wilayah_bencana_sosial":"0","partisipasi_bos":"1","waktu_penyelenggaraan_id":1,"waktu_penyelenggaraan":"Pagi/6 hari","sumber_listrik_id":2,"sumber_listrik":"PLN","sertifikasi_iso_id":2,"sertifikasi_iso":"9001:2008","akses_internet_id":0,"akses_internet":"Tidak Ada","akses_internet_2_id":0,"akses_internet_2":"Tidak Ada","akreditasi":"C","create_date":"2018-02-06T22:59:03.437000","last_update":"2022-03-10T11:08:09.470000"},{"sekolah_id":"60a9815c-0c26-e111-8f7f-e7e4544c6ddc","semester_id":"20222","nama":"SD NEGERI 074II TANAH PERIUK","nama_nomenklatur":null,"nss":"101100211574","npsn":"10500642","bentuk_pendidikan_id":5,"bentuk_pendidikan":"SD","alamat_jalan":"Tanah Periuk","rt":0,"rw":0,"nama_dusun":"Tanah Periuk","kode_wilayah":"100299AB","kode_desa_kelurahan":"100299AB","desa_kelurahan":"Tanah Periuk","kode_kecamatan":"100299  ","kecamatan":"Kec. Tanah Sepenggal Lintas","kode_kabupaten":"100200  ","kabupaten":"Kab. Bungo","kode_provinsi":"100000  ","provinsi":"Prov. Jambi","kode_pos":"37263","lintang":-1.3998,"bujur":101.9635,"nomor_telepon":"085266389096","nomor_fax":"0","email":"ssdn74tanahperiuk@gmail.com","website":"http://","kebutuhan_khusus_id":0,"kebutuhan_khusus":"Tidak ada","status_sekolah_id":"1","status_sekolah":"NEGERI","sk_pendirian_sekolah":"-","tanggal_sk_pendirian":"1981-01-01","status_kepemilikan_id":2,"status_kepemilikan":"Pemerintah Daerah","yayasan_id":null,"yayasan":null,"sk_izin_operasional":"425/162/Dikbud/2023","tanggal_sk_izin_operasional":"2023-02-22","no_rekening":"3720055660","nama_bank":"GIRO POS","cabang_kcp_unit":"MUARA BUNGO","rekening_atas_nama":"SDN 74/II TANAH PERIUK","mbs":1,"luas_tanah_milik":7466,"luas_tanah_bukan_milik":0,"kode_registrasi":"101711962187276","npwp":"001155928332000               ","nm_wp":"BEND.BOS SDN 74/II TANAH PERIUK","keaktifan":"1","flag":"3  ","daya_listrik":1300,"kontinuitas_listrik":"1","jarak_listrik":0,"wilayah_terpencil":"0","wilayah_perbatasan":"0","wilayah_transmigrasi":"0","wilayah_adat_terpencil":"0","wilayah_bencana_alam":"0","wilayah_bencana_sosial":"0","partisipasi_bos":"1","waktu_penyelenggaraan_id":1,"waktu_penyelenggaraan":"Pagi/6 hari","sumber_listrik_id":2,"sumber_listrik":"PLN","sertifikasi_iso_id":9,"sertifikasi_iso":"Belum Bersertifikat","akses_internet_id":2,"akses_internet":"Telkom Speedy","akses_internet_2_id":2,"akses_internet_2":"Telkom Speedy","akreditasi":"B","create_date":"2018-01-24T12:09:39.813000","last_update":"2023-06-01T21:42:23.703000"},{"sekolah_id":"f30cae3a-7e50-4db3-84e7-ab6b2880744a","semester_id":"20222","nama":"RA/BA/TA RA. BAITURRAHIM","nama_nomenklatur":null,"nss":null,"npsn":"69731220","bentuk_pendidikan_id":34,"bentuk_pendidikan":"RA","alamat_jalan":"JL REMBACANG - DESA EMBACANG GEDANG","rt":null,"rw":null,"nama_dusun":null,"kode_wilayah":"100299AA","kode_desa_kelurahan":"100299AA","desa_kelurahan":"-","kode_kecamatan":"100299  ","kecamatan":"Kec. Tanah Sepenggal Lintas","kode_kabupaten":"100200  ","kabupaten":"Kab. Bungo","kode_provinsi":"100000  ","provinsi":"Prov. Jambi","kode_pos":null,"lintang":-1.3991212,"bujur":102.024037,"nomor_telepon":null,"nomor_fax":null,"email":null,"website":null,"kebutuhan_khusus_id":null,"kebutuhan_khusus":null,"status_sekolah_id":"2","status_sekolah":"SWASTA","sk_pendirian_sekolah":null,"tanggal_sk_pendirian":null,"status_kepemilikan_id":3,"status_kepemilikan":"Yayasan","yayasan_id":null,"yayasan":null,"sk_izin_operasional":"-","tanggal_sk_izin_operasional":null,"no_rekening":null,"nama_bank":null,"cabang_kcp_unit":null,"rekening_atas_nama":null,"mbs":0,"luas_tanah_milik":0,"luas_tanah_bukan_milik":0,"kode_registrasi":"64519215992958","npwp":null,"nm_wp":null,"keaktifan":"1","flag":null,"daya_listrik":null,"kontinuitas_listrik":null,"jarak_listrik":null,"wilayah_terpencil":null,"wilayah_perbatasan":null,"wilayah_transmigrasi":null,"wilayah_adat_terpencil":null,"wilayah_bencana_alam":null,"wilayah_bencana_sosial":null,"partisipasi_bos":null,"waktu_penyelenggaraan_id":null,"waktu_penyelenggaraan":null,"sumber_listrik_id":null,"sumber_listrik":null,"sertifikasi_iso_id":null,"sertifikasi_iso":null,"akses_internet_id":null,"akses_internet":null,"akses_internet_2_id":null,"akses_internet_2":null,"akreditasi":"C","create_date":"2018-02-02T06:51:58.580000","last_update":"2013-11-03T13:40:00"},{"sekolah_id":"5d98c2a0-2ec2-4c15-8dc9-9b960ed7e10c","semester_id":"20222","nama":"MTsS Darul Ma arif","nama_nomenklatur":null,"nss":null,"npsn":"69941460","bentuk_pendidikan_id":10,"bentuk_pendidikan":"MTs","alamat_jalan":"Jl. Lintas Sumatera Km.24 Arah Padang","rt":null,"rw":null,"nama_dusun":null,"kode_wilayah":"100299AL","kode_desa_kelurahan":"100299AL","desa_kelurahan":"-","kode_kecamatan":"100299  ","kecamatan":"Kec. Tanah Sepenggal Lintas","kode_kabupaten":"100200  ","kabupaten":"Kab. Bungo","kode_provinsi":"100000  ","provinsi":"Prov. Jambi","kode_pos":null,"lintang":-1.4,"bujur":101.63,"nomor_telepon":null,"nomor_fax":null,"email":null,"website":null,"kebutuhan_khusus_id":null,"kebutuhan_khusus":null,"status_sekolah_id":"2","status_sekolah":"SWASTA","sk_pendirian_sekolah":null,"tanggal_sk_pendirian":null,"status_kepemilikan_id":4,"status_kepemilikan":"Lainnya","yayasan_id":null,"yayasan":null,"sk_izin_operasional":null,"tanggal_sk_izin_operasional":null,"no_rekening":null,"nama_bank":null,"cabang_kcp_unit":null,"rekening_atas_nama":null,"mbs":0,"luas_tanah_milik":0,"luas_tanah_bukan_milik":0,"kode_registrasi":"176757640380974","npwp":null,"nm_wp":null,"keaktifan":"1","flag":null,"daya_listrik":null,"kontinuitas_listrik":null,"jarak_listrik":null,"wilayah_terpencil":null,"wilayah_perbatasan":null,"wilayah_transmigrasi":null,"wilayah_adat_terpencil":null,"wilayah_bencana_alam":null,"wilayah_bencana_sosial":null,"partisipasi_bos":null,"waktu_penyelenggaraan_id":null,"waktu_penyelenggaraan":null,"sumber_listrik_id":null,"sumber_listrik":null,"sertifikasi_iso_id":null,"sertifikasi_iso":null,"akses_internet_id":null,"akses_internet":null,"akses_internet_2_id":null,"akses_internet_2":null,"akreditasi":"C","create_date":"2018-02-02T06:51:58.580000","last_update":"2016-04-04T09:38:00"},{"sekolah_id":"af0c1c8c-dd04-4ec0-8d16-8976543fde27","semester_id":"20222","nama":"MAS DARUSSALAM","nama_nomenklatur":null,"nss":null,"npsn":"10498909","bentuk_pendidikan_id":16,"bentuk_pendidikan":"MA","alamat_jalan":"JLN.LINTAS SUMATERA KM.19","rt":null,"rw":null,"nama_dusun":null,"kode_wilayah":"100299AD","kode_desa_kelurahan":"100299AD","desa_kelurahan":"-","kode_kecamatan":"100299  ","kecamatan":"Kec. Tanah Sepenggal Lintas","kode_kabupaten":"100200  ","kabupaten":"Kab. Bungo","kode_provinsi":"100000  ","provinsi":"Prov. Jambi","kode_pos":null,"lintang":-1.397438,"bujur":101.950208,"nomor_telepon":null,"nomor_fax":null,"email":null,"website":null,"kebutuhan_khusus_id":null,"kebutuhan_khusus":null,"status_sekolah_id":"2","status_sekolah":"SWASTA","sk_pendirian_sekolah":null,"tanggal_sk_pendirian":null,"status_kepemilikan_id":3,"status_kepemilikan":"Yayasan","yayasan_id":null,"yayasan":null,"sk_izin_operasional":"-","tanggal_sk_izin_operasional":null,"no_rekening":null,"nama_bank":null,"cabang_kcp_unit":null,"rekening_atas_nama":null,"mbs":0,"luas_tanah_milik":0,"luas_tanah_bukan_milik":0,"kode_registrasi":"154052099769565","npwp":null,"nm_wp":null,"keaktifan":"1","flag":null,"daya_listrik":null,"kontinuitas_listrik":null,"jarak_listrik":null,"wilayah_terpencil":null,"wilayah_perbatasan":null,"wilayah_transmigrasi":null,"wilayah_adat_terpencil":null,"wilayah_bencana_alam":null,"wilayah_bencana_sosial":null,"partisipasi_bos":null,"waktu_penyelenggaraan_id":null,"waktu_penyelenggaraan":null,"sumber_listrik_id":null,"sumber_listrik":null,"sertifikasi_iso_id":null,"sertifikasi_iso":null,"akses_internet_id":null,"akses_internet":null,"akses_internet_2_id":null,"akses_internet_2":null,"akreditasi":"B","create_date":"2018-02-02T06:51:58.580000","last_update":"2015-05-03T22:16:00"},{"sekolah_id":"35e08731-2406-498b-b920-0a621c40895f","semester_id":"20222","nama":"MTSS DARUSSALAM","nama_nomenklatur":null,"nss":null,"npsn":"10508220","bentuk_pendidikan_id":10,"bentuk_pendidikan":"MTs","alamat_jalan":"Jl Lintas Sumatra Km 19 Arah Padang, Sungai Tembang","rt":null,"rw":null,"nama_dusun":null,"kode_wilayah":"100299AK","kode_desa_kelurahan":"100299AK","desa_kelurahan":"Sungai Tembang","kode_kecamatan":"100299  ","kecamatan":"Kec. Tanah Sepenggal Lintas","kode_kabupaten":"100200  ","kabupaten":"Kab. Bungo","kode_provinsi":"100000  ","provinsi":"Prov. Jambi","kode_pos":null,"lintang":-1.427941,"bujur":101.928162,"nomor_telepon":null,"nomor_fax":null,"email":null,"website":null,"kebutuhan_khusus_id":null,"kebutuhan_khusus":null,"status_sekolah_id":"2","status_sekolah":"SWASTA","sk_pendirian_sekolah":null,"tanggal_sk_pendirian":null,"status_kepemilikan_id":3,"status_kepemilikan":"Yayasan","yayasan_id":null,"yayasan":null,"sk_izin_operasional":"-","tanggal_sk_izin_operasional":null,"no_rekening":null,"nama_bank":null,"cabang_kcp_unit":null,"rekening_atas_nama":null,"mbs":0,"luas_tanah_milik":0,"luas_tanah_bukan_milik":0,"kode_registrasi":"54459651917348","npwp":null,"nm_wp":null,"keaktifan":"1","flag":null,"daya_listrik":null,"kontinuitas_listrik":null,"jarak_listrik":null,"wilayah_terpencil":null,"wilayah_perbatasan":null,"wilayah_transmigrasi":null,"wilayah_adat_terpencil":null,"wilayah_bencana_alam":null,"wilayah_bencana_sosial":null,"partisipasi_bos":null,"waktu_penyelenggaraan_id":null,"waktu_penyelenggaraan":null,"sumber_listrik_id":null,"sumber_listrik":null,"sertifikasi_iso_id":null,"sertifikasi_iso":null,"akses_internet_id":null,"akses_internet":null,"akses_internet_2_id":null,"akses_internet_2":null,"akreditasi":"C","create_date":"2018-02-02T06:51:58.580000","last_update":"2019-11-11T07:49:25.400000"},{"sekolah_id":"56410fb1-60bf-4c8b-b2a0-c9626c465efd","semester_id":"20222","nama":"KB ASSYIFA","nama_nomenklatur":null,"nss":"****        ","npsn":"69886809","bentuk_pendidikan_id":2,"bentuk_pendidikan":"KB","alamat_jalan":"BETUNG","rt":null,"rw":null,"nama_dusun":"Lubuk Landai","kode_wilayah":"100299AE","kode_desa_kelurahan":"100299AE","desa_kelurahan":"LUBUK LANDAI","kode_kecamatan":"100299  ","kecamatan":"Kec. Tanah Sepenggal Lintas","kode_kabupaten":"100200  ","kabupaten":"Kab. Bungo","kode_provinsi":"100000  ","provinsi":"Prov. Jambi","kode_pos":"37263","lintang":0.0,"bujur":0.0,"nomor_telepon":null,"nomor_fax":null,"email":"assyfa@yahoo.com","website":"http://","kebutuhan_khusus_id":0,"kebutuhan_khusus":"Tidak ada","status_sekolah_id":"2","status_sekolah":"SWASTA","sk_pendirian_sekolah":null,"tanggal_sk_pendirian":null,"status_kepemilikan_id":3,"status_kepemilikan":"Yayasan","yayasan_id":"6ae827ac-69cc-41be-9301-5f8fbce1e5f8","yayasan":"PKBM Assyifa","sk_izin_operasional":"74 TAHUN 2009","tanggal_sk_izin_operasional":null,"no_rekening":"3004193082","nama_bank":"BPD JAMBI","cabang_kcp_unit":"Cabang Ma Bungo","rekening_atas_nama":"69886809 KB ASSYIFA","mbs":0,"luas_tanah_milik":480,"luas_tanah_bukan_milik":0,"kode_registrasi":"194679078829920","npwp":"152518841332000               ","nm_wp":null,"keaktifan":"1","flag":null,"daya_listrik":1300,"kontinuitas_listrik":"1","jarak_listrik":0,"wilayah_terpencil":"0","wilayah_perbatasan":"0","wilayah_transmigrasi":"0","wilayah_adat_terpencil":"0","wilayah_bencana_alam":"0","wilayah_bencana_sosial":"0","partisipasi_bos":"1","waktu_penyelenggaraan_id":1,"waktu_penyelenggaraan":"Pagi/6 hari","sumber_listrik_id":2,"sumber_listrik":"PLN","sertifikasi_iso_id":9,"sertifikasi_iso":"Belum Bersertifikat","akses_internet_id":4,"akses_internet":"Telkomsel Flash","akses_internet_2_id":4,"akses_internet_2":"Telkomsel Flash","akreditasi":"C","create_date":"2018-02-06T22:59:03.437000","last_update":"2015-08-27T12:47:00"},{"sekolah_id":"5e92f564-b9e1-4bff-8979-b565537d18b3","semester_id":"20222","nama":"PKBM CAHAYA","nama_nomenklatur":null,"nss":"****        ","npsn":"P9934532","bentuk_pendidikan_id":27,"bentuk_pendidikan":"PKBM","alamat_jalan":"Desa Sungai Tembang","rt":3,"rw":1,"nama_dusun":null,"kode_wilayah":"100299AK","kode_desa_kelurahan":"100299AK","desa_kelurahan":"Sungai Tembang","kode_kecamatan":"100299  ","kecamatan":"Kec. Tanah Sepenggal Lintas","kode_kabupaten":"100200  ","kabupaten":"Kab. Bungo","kode_provinsi":"100000  ","provinsi":"Prov. Jambi","kode_pos":"37263","lintang":-1.392,"bujur":102.0321,"nomor_telepon":"081366611126","nomor_fax":null,"email":null,"website":"http://","kebutuhan_khusus_id":0,"kebutuhan_khusus":"Tidak ada","status_sekolah_id":"2","status_sekolah":"SWASTA","sk_pendirian_sekolah":"32","tanggal_sk_pendirian":"2012-02-10","status_kepemilikan_id":3,"status_kepemilikan":"Yayasan","yayasan_id":null,"yayasan":null,"sk_izin_operasional":"33","tanggal_sk_izin_operasional":"2012-02-08","no_rekening":"3004195228","nama_bank":"BPD JAMBI","cabang_kcp_unit":"Muara Bungo","rekening_atas_nama":"P9934532 PKBM CAHAYA","mbs":0,"luas_tanah_milik":596,"luas_tanah_bukan_milik":0,"kode_registrasi":"111005885456825","npwp":"026941021332000               ","nm_wp":"Yayasan PKBM Cahaya","keaktifan":"1","flag":null,"daya_listrik":900,"kontinuitas_listrik":"1","jarak_listrik":0,"wilayah_terpencil":"0","wilayah_perbatasan":"0","wilayah_transmigrasi":"0","wilayah_adat_terpencil":"0","wilayah_bencana_alam":"0","wilayah_bencana_sosial":"0","partisipasi_bos":"1","waktu_penyelenggaraan_id":1,"waktu_penyelenggaraan":"Pagi/6 hari","sumber_listrik_id":2,"sumber_listrik":"PLN","sertifikasi_iso_id":9,"sertifikasi_iso":"Belum Bersertifikat","akses_internet_id":4,"akses_internet":"Telkomsel Flash","akses_internet_2_id":4,"akses_internet_2":"Telkomsel Flash","akreditasi":"C","create_date":"2018-02-06T22:59:03.437000","last_update":"2022-03-10T11:08:09.470000"},{"sekolah_id":"48e80f0a-4d9c-486d-908b-30b54d252739","semester_id":"20222","nama":"TK CAHAYA","nama_nomenklatur":null,"nss":null,"npsn":"70029138","bentuk_pendidikan_id":1,"bentuk_pendidikan":"TK","alamat_jalan":"Desa Sungai Tembang","rt":null,"rw":null,"nama_dusun":null,"kode_wilayah":"100299AK","kode_desa_kelurahan":"100299AK","desa_kelurahan":"Sungai Tembang","kode_kecamatan":"100299  ","kecamatan":"Kec. Tanah Sepenggal Lintas","kode_kabupaten":"100200  ","kabupaten":"Kab. Bungo","kode_provinsi":"100000  ","provinsi":"Prov. Jambi","kode_pos":null,"lintang":0.0,"bujur":0.0,"nomor_telepon":null,"nomor_fax":null,"email":null,"website":"http://","kebutuhan_khusus_id":0,"kebutuhan_khusus":"Tidak ada","status_sekolah_id":"2","status_sekolah":"SWASTA","sk_pendirian_sekolah":"32","tanggal_sk_pendirian":"2012-02-10","status_kepemilikan_id":3,"status_kepemilikan":"Yayasan","yayasan_id":null,"yayasan":null,"sk_izin_operasional":"503/302/IPSP-TK/DPMPTSP","tanggal_sk_izin_operasional":"2022-04-25","no_rekening":null,"nama_bank":null,"cabang_kcp_unit":null,"rekening_atas_nama":null,"mbs":0,"luas_tanah_milik":597,"luas_tanah_bukan_milik":0,"kode_registrasi":"11063437859917","npwp":null,"nm_wp":null,"keaktifan":"1","flag":null,"daya_listrik":900,"kontinuitas_listrik":"1","jarak_listrik":0,"wilayah_terpencil":"0","wilayah_perbatasan":"0","wilayah_transmigrasi":"0","wilayah_adat_terpencil":"0","wilayah_bencana_alam":"0","wilayah_bencana_sosial":"0","partisipasi_bos":"1","waktu_penyelenggaraan_id":1,"waktu_penyelenggaraan":"Pagi/6 hari","sumber_listrik_id":2,"sumber_listrik":"PLN","sertifikasi_iso_id":9,"sertifikasi_iso":"Belum Bersertifikat","akses_internet_id":4,"akses_internet":"Telkomsel Flash","akses_internet_2_id":4,"akses_internet_2":"Telkomsel Flash","akreditasi":null,"create_date":"2022-05-31T00:00:38.200000","last_update":"2022-05-30T15:38:16.410000"},{"sekolah_id":"85696c49-b9e2-4885-917a-c4d0c679d458","semester_id":"20222","nama":"KB PUJAAN HATI","nama_nomenklatur":null,"nss":"****        ","npsn":"69791838","bentuk_pendidikan_id":2,"bentuk_pendidikan":"KB","alamat_jalan":"Desa Paku Aji","rt":null,"rw":null,"nama_dusun":"PAKU AJI","kode_wilayah":"100299AI","kode_desa_kelurahan":"100299AI","desa_kelurahan":"Paku Aji","kode_kecamatan":"100299  ","kecamatan":"Kec. Tanah Sepenggal Lintas","kode_kabupaten":"100200  ","kabupaten":"Kab. Bungo","kode_provinsi":"100000  ","provinsi":"Prov. Jambi","kode_pos":"37263","lintang":-1.4024,"bujur":101.9072,"nomor_telepon":null,"nomor_fax":null,"email":"paudpujaan.hati@gmail.com","website":"http://","kebutuhan_khusus_id":0,"kebutuhan_khusus":"Tidak ada","status_sekolah_id":"2","status_sekolah":"SWASTA","sk_pendirian_sekolah":"06","tanggal_sk_pendirian":"2009-10-14","status_kepemilikan_id":3,"status_kepemilikan":"Yayasan","yayasan_id":"3621d00d-98a8-446c-b6e7-9eec880e16e0","yayasan":"YAYASAN PUJAAN HATI","sk_izin_operasional":"2456","tanggal_sk_izin_operasional":"2011-07-07","no_rekening":"3004194577","nama_bank":"BPD JAMBI","cabang_kcp_unit":"Cabang Ma Bungo","rekening_atas_nama":"69791838 KB PUJAAN HATI","mbs":0,"luas_tanah_milik":450,"luas_tanah_bukan_milik":0,"kode_registrasi":"80729975677625","npwp":"723700894332000               ","nm_wp":null,"keaktifan":"1","flag":null,"daya_listrik":1300,"kontinuitas_listrik":"2","jarak_listrik":0,"wilayah_terpencil":"0","wilayah_perbatasan":"0","wilayah_transmigrasi":"0","wilayah_adat_terpencil":"0","wilayah_bencana_alam":"0","wilayah_bencana_sosial":"0","partisipasi_bos":"1","waktu_penyelenggaraan_id":1,"waktu_penyelenggaraan":"Pagi/6 hari","sumber_listrik_id":2,"sumber_listrik":"PLN","sertifikasi_iso_id":9,"sertifikasi_iso":"Belum Bersertifikat","akses_internet_id":99,"akses_internet":"Lainnya","akses_internet_2_id":4,"akses_internet_2":"Telkomsel Flash","akreditasi":"C","create_date":"2018-02-06T22:59:03.437000","last_update":"2022-03-10T11:08:09.470000"},{"sekolah_id":"101b045c-0c26-e111-9d82-e574a72a5c25","semester_id":"20222","nama":"SD NEGERI 223II SIMPANG RANTAU EMBACANG","nama_nomenklatur":null,"nss":"101100240223","npsn":"10500774","bentuk_pendidikan_id":5,"bentuk_pendidikan":"SD","alamat_jalan":"Simpang Rantau Embacang","rt":0,"rw":0,"nama_dusun":"RANTAU MAKMUR","kode_wilayah":"100299AH","kode_desa_kelurahan":"100299AH","desa_kelurahan":"Rantau Embacang","kode_kecamatan":"100299  ","kecamatan":"Kec. Tanah Sepenggal Lintas","kode_kabupaten":"100200  ","kabupaten":"Kab. Bungo","kode_provinsi":"100000  ","provinsi":"Prov. Jambi","kode_pos":"37263","lintang":-1.3846,"bujur":101.9101,"nomor_telepon":null,"nomor_fax":null,"email":"sdn223simp_rantaueembacang@yahoo.com","website":"http://","kebutuhan_khusus_id":0,"kebutuhan_khusus":"Tidak ada","status_sekolah_id":"1","status_sekolah":"NEGERI","sk_pendirian_sekolah":"","tanggal_sk_pendirian":"2001-04-01","status_kepemilikan_id":2,"status_kepemilikan":"Pemerintah Daerah","yayasan_id":null,"yayasan":null,"sk_izin_operasional":"-","tanggal_sk_izin_operasional":"1910-01-01","no_rekening":"0204027013","nama_bank":"BANK JAMBI","cabang_kcp_unit":"cabang","rekening_atas_nama":"SDN NO 223/II SIMP. RANTAU EMBACANG","mbs":0,"luas_tanah_milik":11000,"luas_tanah_bukan_milik":0,"kode_registrasi":"101172703667724","npwp":"001155928332000               ","nm_wp":"SDN 223/II RANTAU EMBACANG","keaktifan":"1","flag":null,"daya_listrik":900,"kontinuitas_listrik":"1","jarak_listrik":0,"wilayah_terpencil":"0","wilayah_perbatasan":"0","wilayah_transmigrasi":"0","wilayah_adat_terpencil":"0","wilayah_bencana_alam":"0","wilayah_bencana_sosial":"0","partisipasi_bos":"1","waktu_penyelenggaraan_id":1,"waktu_penyelenggaraan":"Pagi/6 hari","sumber_listrik_id":2,"sumber_listrik":"PLN","sertifikasi_iso_id":9,"sertifikasi_iso":"Belum Bersertifikat","akses_internet_id":0,"akses_internet":"Tidak Ada","akses_internet_2_id":4,"akses_internet_2":"Telkomsel Flash","akreditasi":"B","create_date":"2018-01-24T12:09:39.813000","last_update":"2023-03-09T14:52:22.423000"},{"sekolah_id":"706eae61-0c26-e111-a6eb-cf794f0b2bee","semester_id":"20222","nama":"SMP NEGERI 03 TANAH SEPENGGAL","nama_nomenklatur":null,"nss":"201100204019","npsn":"10500731","bentuk_pendidikan_id":6,"bentuk_pendidikan":"SMP","alamat_jalan":"Desa Rantau Embacang","rt":4,"rw":0,"nama_dusun":"RANTAU EMBACANG","kode_wilayah":"100299AH","kode_desa_kelurahan":"100299AH","desa_kelurahan":"Rantau Embacang","kode_kecamatan":"100299  ","kecamatan":"Kec. Tanah Sepenggal Lintas","kode_kabupaten":"100200  ","kabupaten":"Kab. Bungo","kode_provinsi":"100000  ","provinsi":"Prov. Jambi","kode_pos":"37263","lintang":-1.3965,"bujur":101.9157,"nomor_telepon":"082283069723","nomor_fax":null,"email":"sekmenpern3tasep@gmail.com","website":"http://","kebutuhan_khusus_id":0,"kebutuhan_khusus":"Tidak ada","status_sekolah_id":"1","status_sekolah":"NEGERI","sk_pendirian_sekolah":"018/C/KEP/I-983","tanggal_sk_pendirian":"1983-02-23","status_kepemilikan_id":2,"status_kepemilikan":"Pemerintah Daerah","yayasan_id":null,"yayasan":null,"sk_izin_operasional":"J 03032003","tanggal_sk_izin_operasional":"1989-01-14","no_rekening":"3002419326","nama_bank":"BPD JAMBI...","cabang_kcp_unit":"BPD JAMBI CABANG BUNGO...","rekening_atas_nama":"DNBOSSMPN3TANAHSEPENGGAL...","mbs":1,"luas_tanah_milik":17195,"luas_tanah_bukan_milik":0,"kode_registrasi":"107401805047308","npwp":"001155928332000               ","nm_wp":"SMP Negeri 3 Tanah Sepenggal","keaktifan":"1","flag":null,"daya_listrik":900,"kontinuitas_listrik":"1","jarak_listrik":0,"wilayah_terpencil":"0","wilayah_perbatasan":"0","wilayah_transmigrasi":"0","wilayah_adat_terpencil":"0","wilayah_bencana_alam":"0","wilayah_bencana_sosial":"0","partisipasi_bos":"1","waktu_penyelenggaraan_id":1,"waktu_penyelenggaraan":"Pagi/6 hari","sumber_listrik_id":2,"sumber_listrik":"PLN","sertifikasi_iso_id":9,"sertifikasi_iso":"Belum Bersertifikat","akses_internet_id":94,"akses_internet":"Lainnya (Satelit)","akses_internet_2_id":99,"akses_internet_2":"Lainnya","akreditasi":"B","create_date":"2018-01-24T12:09:39.813000","last_update":"2022-07-28T06:02:39.653000"},{"sekolah_id":"d337095e-d611-4bec-ab0c-42b13495a619","semester_id":"20222","nama":"TK PERTIWI II","nama_nomenklatur":null,"nss":"******      ","npsn":"10506352","bentuk_pendidikan_id":1,"bentuk_pendidikan":"TK","alamat_jalan":"DESA TANAH PERIUK","rt":null,"rw":null,"nama_dusun":"TANAH PERIUK","kode_wilayah":"100299AB","kode_desa_kelurahan":"100299AB","desa_kelurahan":"Tanah Periuk","kode_kecamatan":"100299  ","kecamatan":"Kec. Tanah Sepenggal Lintas","kode_kabupaten":"100200  ","kabupaten":"Kab. Bungo","kode_provinsi":"100000  ","provinsi":"Prov. Jambi","kode_pos":"37263","lintang":0.0,"bujur":0.0,"nomor_telepon":null,"nomor_fax":null,"email":"tkpertiwitanahperiuk204@gmail.com","website":"http://","kebutuhan_khusus_id":0,"kebutuhan_khusus":"Tidak ada","status_sekolah_id":"2","status_sekolah":"SWASTA","sk_pendirian_sekolah":"250","tanggal_sk_pendirian":"2006-10-21","status_kepemilikan_id":3,"status_kepemilikan":"Yayasan","yayasan_id":"41c34ce5-6009-4b65-b974-a97c2faa153d","yayasan":"TK PERTIWI II","sk_izin_operasional":"250","tanggal_sk_izin_operasional":"2006-10-21","no_rekening":"3004192997","nama_bank":"BPD JAMBI","cabang_kcp_unit":"Cabang Ma Bungo","rekening_atas_nama":"10506352 TK PERTIWI II","mbs":0,"luas_tanah_milik":700,"luas_tanah_bukan_milik":700,"kode_registrasi":"103393684296150","npwp":"714298247332000               ","nm_wp":null,"keaktifan":"1","flag":null,"daya_listrik":0,"kontinuitas_listrik":"1","jarak_listrik":0,"wilayah_terpencil":"0","wilayah_perbatasan":"0","wilayah_transmigrasi":"0","wilayah_adat_terpencil":"0","wilayah_bencana_alam":"0","wilayah_bencana_sosial":"0","partisipasi_bos":"1","waktu_penyelenggaraan_id":1,"waktu_penyelenggaraan":"Pagi/6 hari","sumber_listrik_id":7,"sumber_listrik":"Menumpang","sertifikasi_iso_id":9,"sertifikasi_iso":"Belum Bersertifikat","akses_internet_id":4,"akses_internet":"Telkomsel Flash","akses_internet_2_id":4,"akses_internet_2":"Telkomsel Flash","akreditasi":"C","create_date":"2018-02-06T22:59:03.437000","last_update":"2016-06-13T11:58:00"},{"sekolah_id":"507a815c-0c26-e111-8c8c-73c4caa4b9ea","semester_id":"20222","nama":"SD NEGERI 073II SIMP. SUNGAI MANCUR","nama_nomenklatur":null,"nss":"101100204073","npsn":"10500641","bentuk_pendidikan_id":5,"bentuk_pendidikan":"SD","alamat_jalan":"Simp. Sungai Mancur","rt":0,"rw":0,"nama_dusun":"Sungai Tembang","kode_wilayah":"100299AK","kode_desa_kelurahan":"100299AK","desa_kelurahan":"Sungai Tembang","kode_kecamatan":"100299  ","kecamatan":"Kec. Tanah Sepenggal Lintas","kode_kabupaten":"100200  ","kabupaten":"Kab. Bungo","kode_provinsi":"100000  ","provinsi":"Prov. Jambi","kode_pos":"37263","lintang":-1.4005,"bujur":102.0038,"nomor_telepon":"082176404405","nomor_fax":null,"email":"sdn73sungaimancur@gmail.com","website":"http://","kebutuhan_khusus_id":0,"kebutuhan_khusus":"Tidak ada","status_sekolah_id":"1","status_sekolah":"NEGERI","sk_pendirian_sekolah":"-","tanggal_sk_pendirian":"1980-01-18","status_kepemilikan_id":2,"status_kepemilikan":"Pemerintah Daerah","yayasan_id":null,"yayasan":null,"sk_izin_operasional":"-","tanggal_sk_izin_operasional":"1910-01-01","no_rekening":"0204003343","nama_bank":"BANK 9 JAMBI ( SEGIN","cabang_kcp_unit":"cabang","rekening_atas_nama":"SDN 73/II Simpang Sungai Mancur.","mbs":1,"luas_tanah_milik":3648,"luas_tanah_bukan_milik":0,"kode_registrasi":"101711172609548","npwp":"001155928332000               ","nm_wp":null,"keaktifan":"1","flag":null,"daya_listrik":1300,"kontinuitas_listrik":"1","jarak_listrik":0,"wilayah_terpencil":"0","wilayah_perbatasan":"0","wilayah_transmigrasi":"0","wilayah_adat_terpencil":"0","wilayah_bencana_alam":"0","wilayah_bencana_sosial":"0","partisipasi_bos":"1","waktu_penyelenggaraan_id":1,"waktu_penyelenggaraan":"Pagi/6 hari","sumber_listrik_id":2,"sumber_listrik":"PLN","sertifikasi_iso_id":9,"sertifikasi_iso":"Belum Bersertifikat","akses_internet_id":4,"akses_internet":"Telkomsel Flash","akses_internet_2_id":91,"akses_internet_2":"Lainnya (Kabel)","akreditasi":"B","create_date":"2018-01-24T12:09:39.813000","last_update":"2022-03-10T11:08:09.470000"},{"sekolah_id":"908550fd-7405-48e2-8bac-4cc573089891","semester_id":"20222","nama":"KB KASIH IBU","nama_nomenklatur":null,"nss":"****        ","npsn":"69791913","bentuk_pendidikan_id":2,"bentuk_pendidikan":"KB","alamat_jalan":"Sungai Lilin","rt":null,"rw":null,"nama_dusun":"DUSUN SUNGAI LILIN","kode_wilayah":"100299AC","kode_desa_kelurahan":"100299AC","desa_kelurahan":"Sungai Lilin","kode_kecamatan":"100299  ","kecamatan":"Kec. Tanah Sepenggal Lintas","kode_kabupaten":"100200  ","kabupaten":"Kab. Bungo","kode_provinsi":"100000  ","provinsi":"Prov. Jambi","kode_pos":null,"lintang":-5.443757,"bujur":114.421127,"nomor_telepon":"081274214142","nomor_fax":null,"email":null,"website":"http://","kebutuhan_khusus_id":0,"kebutuhan_khusus":"Tidak ada","status_sekolah_id":"2","status_sekolah":"SWASTA","sk_pendirian_sekolah":"37","tanggal_sk_pendirian":"2009-04-18","status_kepemilikan_id":4,"status_kepemilikan":"Lainnya","yayasan_id":"ee38489f-6627-4843-8c4a-237e49fee854","yayasan":"PAUD KASIH IBU","sk_izin_operasional":"37 tahun 2009","tanggal_sk_izin_operasional":"2009-04-18","no_rekening":"3004192817","nama_bank":"BPD JAMBI","cabang_kcp_unit":"Cabang Ma Bungo","rekening_atas_nama":"69791913 KB KASIH IBU","mbs":0,"luas_tanah_milik":800,"luas_tanah_bukan_milik":0,"kode_registrasi":"278522280019316","npwp":"026938100332000               ","nm_wp":null,"keaktifan":"1","flag":null,"daya_listrik":1300,"kontinuitas_listrik":"1","jarak_listrik":0,"wilayah_terpencil":"0","wilayah_perbatasan":"0","wilayah_transmigrasi":"0","wilayah_adat_terpencil":"0","wilayah_bencana_alam":"0","wilayah_bencana_sosial":"0","partisipasi_bos":"1","waktu_penyelenggaraan_id":1,"waktu_penyelenggaraan":"Pagi/6 hari","sumber_listrik_id":2,"sumber_listrik":"PLN","sertifikasi_iso_id":9,"sertifikasi_iso":"Belum Bersertifikat","akses_internet_id":0,"akses_internet":"Tidak Ada","akses_internet_2_id":4,"akses_internet_2":"Telkomsel Flash","akreditasi":"C","create_date":"2018-02-06T22:59:03.437000","last_update":"2022-03-10T11:08:09.470000"},{"sekolah_id":"c0d96a5c-0c26-e111-8487-cde71fab6658","semester_id":"20222","nama":"SD NEGERI 193II SUNGAI PURI","nama_nomenklatur":null,"nss":"101100202081","npsn":"10500745","bentuk_pendidikan_id":5,"bentuk_pendidikan":"SD","alamat_jalan":"Desa Sungai Puri","rt":0,"rw":0,"nama_dusun":"SUNGAI PURI","kode_wilayah":"100299AJ","kode_desa_kelurahan":"100299AJ","desa_kelurahan":"SUNGAI PURI","kode_kecamatan":"100299  ","kecamatan":"Kec. Tanah Sepenggal Lintas","kode_kabupaten":"100200  ","kabupaten":"Kab. Bungo","kode_provinsi":"100000  ","provinsi":"Prov. Jambi","kode_pos":"37263","lintang":-1.4103,"bujur":101.9034,"nomor_telepon":"082372401391","nomor_fax":null,"email":"sekolahsd193saipuri@gmail.com","website":"http://www.sekolahsd193saipuri@gmail.com","kebutuhan_khusus_id":0,"kebutuhan_khusus":"Tidak ada","status_sekolah_id":"1","status_sekolah":"NEGERI","sk_pendirian_sekolah":"-","tanggal_sk_pendirian":"1986-01-01","status_kepemilikan_id":1,"status_kepemilikan":"Pemerintah Pusat","yayasan_id":null,"yayasan":null,"sk_izin_operasional":"-","tanggal_sk_izin_operasional":"1910-01-01","no_rekening":"3001764232","nama_bank":"BPD","cabang_kcp_unit":"cabang","rekening_atas_nama":"SD 193/II Sungai Puri","mbs":1,"luas_tanah_milik":4450,"luas_tanah_bukan_milik":0,"kode_registrasi":"101613989537292","npwp":"001155928332000               ","nm_wp":"BENDAHARA BOS SD NO 193/II SUNGAI PURI","keaktifan":"1","flag":null,"daya_listrik":900,"kontinuitas_listrik":"1","jarak_listrik":0,"wilayah_terpencil":"0","wilayah_perbatasan":"0","wilayah_transmigrasi":"0","wilayah_adat_terpencil":"0","wilayah_bencana_alam":"0","wilayah_bencana_sosial":"0","partisipasi_bos":"1","waktu_penyelenggaraan_id":1,"waktu_penyelenggaraan":"Pagi/6 hari","sumber_listrik_id":2,"sumber_listrik":"PLN","sertifikasi_iso_id":9,"sertifikasi_iso":"Belum Bersertifikat","akses_internet_id":0,"akses_internet":"Tidak Ada","akses_internet_2_id":0,"akses_internet_2":"Tidak Ada","akreditasi":"C","create_date":"2018-01-24T12:09:39.813000","last_update":"2022-03-10T11:08:09.470000"},{"sekolah_id":"d7b345f4-7349-457c-92cc-69c3d2bc5c4b","semester_id":"20222","nama":"MTs ALHUSNA LUBUK LANDAI SUNGAI LILIN","nama_nomenklatur":null,"nss":null,"npsn":"70025955","bentuk_pendidikan_id":10,"bentuk_pendidikan":"MTs","alamat_jalan":"JL. LINTAS SUMATERA KM. 19 ARAH PADANG","rt":null,"rw":null,"nama_dusun":null,"kode_wilayah":"100299AC","kode_desa_kelurahan":"100299AC","desa_kelurahan":"Sungai Lilin","kode_kecamatan":"100299  ","kecamatan":"Kec. Tanah Sepenggal Lintas","kode_kabupaten":"100200  ","kabupaten":"Kab. Bungo","kode_provinsi":"100000  ","provinsi":"Prov. Jambi","kode_pos":null,"lintang":-1.3895,"bujur":101.9608,"nomor_telepon":null,"nomor_fax":null,"email":null,"website":null,"kebutuhan_khusus_id":null,"kebutuhan_khusus":null,"status_sekolah_id":"2","status_sekolah":"SWASTA","sk_pendirian_sekolah":"07 TAHUN 2021","tanggal_sk_pendirian":"2021-07-02","status_kepemilikan_id":3,"status_kepemilikan":"Yayasan","yayasan_id":null,"yayasan":null,"sk_izin_operasional":"07 TAHUN 2021","tanggal_sk_izin_operasional":"2021-07-02","no_rekening":null,"nama_bank":null,"cabang_kcp_unit":null,"rekening_atas_nama":null,"mbs":0,"luas_tanah_milik":0,"luas_tanah_bukan_milik":15000,"kode_registrasi":"268580207151475","npwp":null,"nm_wp":null,"keaktifan":"1","flag":null,"daya_listrik":null,"kontinuitas_listrik":null,"jarak_listrik":null,"wilayah_terpencil":null,"wilayah_perbatasan":null,"wilayah_transmigrasi":null,"wilayah_adat_terpencil":null,"wilayah_bencana_alam":null,"wilayah_bencana_sosial":null,"partisipasi_bos":null,"waktu_penyelenggaraan_id":null,"waktu_penyelenggaraan":null,"sumber_listrik_id":null,"sumber_listrik":null,"sertifikasi_iso_id":null,"sertifikasi_iso":null,"akses_internet_id":null,"akses_internet":null,"akses_internet_2_id":null,"akses_internet_2":null,"akreditasi":null,"create_date":"2022-02-22T00:00:31.820000","last_update":"2022-08-01T05:45:59.463000"},{"sekolah_id":"89154683-2c43-443c-8e06-d8aff36803d2","semester_id":"20222","nama":"MA ALHUSNA LUBUK LANDAI SUNGAI LILIN","nama_nomenklatur":null,"nss":null,"npsn":"70025932","bentuk_pendidikan_id":16,"bentuk_pendidikan":"MA","alamat_jalan":"JL. LINTAS SUMATERA KM.24 ARAH PADANG RT.08/RW.01","rt":null,"rw":null,"nama_dusun":null,"kode_wilayah":"100299AC","kode_desa_kelurahan":"100299AC","desa_kelurahan":"SUNGAI LILIN","kode_kecamatan":"100299  ","kecamatan":"Kec. Tanah Sepenggal Lintas","kode_kabupaten":"100200  ","kabupaten":"Kab. Bungo","kode_provinsi":"100000  ","provinsi":"Prov. Jambi","kode_pos":null,"lintang":0.0,"bujur":0.0,"nomor_telepon":null,"nomor_fax":null,"email":null,"website":null,"kebutuhan_khusus_id":null,"kebutuhan_khusus":null,"status_sekolah_id":"2","status_sekolah":"SWASTA","sk_pendirian_sekolah":null,"tanggal_sk_pendirian":null,"status_kepemilikan_id":3,"status_kepemilikan":"Yayasan","yayasan_id":null,"yayasan":null,"sk_izin_operasional":"08 TAHUN 2021","tanggal_sk_izin_operasional":"2021-07-02","no_rekening":null,"nama_bank":null,"cabang_kcp_unit":null,"rekening_atas_nama":null,"mbs":0,"luas_tanah_milik":635,"luas_tanah_bukan_milik":15000,"kode_registrasi":"144337032266540","npwp":null,"nm_wp":null,"keaktifan":"1","flag":null,"daya_listrik":null,"kontinuitas_listrik":null,"jarak_listrik":null,"wilayah_terpencil":null,"wilayah_perbatasan":null,"wilayah_transmigrasi":null,"wilayah_adat_terpencil":null,"wilayah_bencana_alam":null,"wilayah_bencana_sosial":null,"partisipasi_bos":null,"waktu_penyelenggaraan_id":null,"waktu_penyelenggaraan":null,"sumber_listrik_id":null,"sumber_listrik":null,"sertifikasi_iso_id":null,"sertifikasi_iso":null,"akses_internet_id":null,"akses_internet":null,"akses_internet_2_id":null,"akses_internet_2":null,"akreditasi":null,"create_date":"2022-02-22T00:00:31.820000","last_update":"2022-02-21T10:09:38.510000"},{"sekolah_id":"b58cd4e7-f535-4f01-804b-43c03cf6ff4f","semester_id":"20222","nama":"KB PELANGI MAKMUR","nama_nomenklatur":null,"nss":"****        ","npsn":"69886812","bentuk_pendidikan_id":2,"bentuk_pendidikan":"KB","alamat_jalan":"RANTAU MAKMUR","rt":3,"rw":null,"nama_dusun":"rantau makmur","kode_wilayah":"100299AH","kode_desa_kelurahan":"100299AH","desa_kelurahan":"RANTAU EMBACANG","kode_kecamatan":"100299  ","kecamatan":"Kec. Tanah Sepenggal Lintas","kode_kabupaten":"100200  ","kabupaten":"Kab. Bungo","kode_provinsi":"100000  ","provinsi":"Prov. Jambi","kode_pos":"37263","lintang":0.0,"bujur":0.0,"nomor_telepon":null,"nomor_fax":null,"email":null,"website":"http://","kebutuhan_khusus_id":0,"kebutuhan_khusus":"Tidak ada","status_sekolah_id":"2","status_sekolah":"SWASTA","sk_pendirian_sekolah":null,"tanggal_sk_pendirian":null,"status_kepemilikan_id":4,"status_kepemilikan":"Lainnya","yayasan_id":"84fcc868-38a6-418a-9ded-c4666547fb5f","yayasan":"PELANGI MAKMUR","sk_izin_operasional":"11 TAHUN 2014","tanggal_sk_izin_operasional":null,"no_rekening":"3004192833","nama_bank":"BPD JAMBI","cabang_kcp_unit":"Cabang Ma Bungo","rekening_atas_nama":"69886812 KB PELANGI MAKMUR","mbs":0,"luas_tanah_milik":300,"luas_tanah_bukan_milik":0,"kode_registrasi":"254900079769077","npwp":"662630110332000               ","nm_wp":null,"keaktifan":"1","flag":null,"daya_listrik":0,"kontinuitas_listrik":"1","jarak_listrik":0,"wilayah_terpencil":"0","wilayah_perbatasan":"0","wilayah_transmigrasi":"0","wilayah_adat_terpencil":"0","wilayah_bencana_alam":"0","wilayah_bencana_sosial":"0","partisipasi_bos":"1","waktu_penyelenggaraan_id":1,"waktu_penyelenggaraan":"Pagi/6 hari","sumber_listrik_id":7,"sumber_listrik":"Menumpang","sertifikasi_iso_id":9,"sertifikasi_iso":"Belum Bersertifikat","akses_internet_id":4,"akses_internet":"Telkomsel Flash","akses_internet_2_id":4,"akses_internet_2":"Telkomsel Flash","akreditasi":null,"create_date":"2018-02-06T22:59:03.437000","last_update":"2022-03-10T11:08:09.470000"},{"sekolah_id":"1efefed9-6e74-40cf-a08f-dd340adf6a06","semester_id":"20222","nama":"KB NUSANTARA","nama_nomenklatur":null,"nss":"****        ","npsn":"69791950","bentuk_pendidikan_id":2,"bentuk_pendidikan":"KB","alamat_jalan":"TELUK PANDAK","rt":4,"rw":null,"nama_dusun":"Embacang Gedang","kode_wilayah":"100299AA","kode_desa_kelurahan":"100299AA","desa_kelurahan":"EMBACANG GEDANG","kode_kecamatan":"100299  ","kecamatan":"Kec. Tanah Sepenggal Lintas","kode_kabupaten":"100200  ","kabupaten":"Kab. Bungo","kode_provinsi":"100000  ","provinsi":"Prov. Jambi","kode_pos":null,"lintang":-1.399159,"bujur":102.02239,"nomor_telepon":null,"nomor_fax":null,"email":null,"website":"http://","kebutuhan_khusus_id":0,"kebutuhan_khusus":"Tidak ada","status_sekolah_id":"2","status_sekolah":"SWASTA","sk_pendirian_sekolah":null,"tanggal_sk_pendirian":null,"status_kepemilikan_id":4,"status_kepemilikan":"Lainnya","yayasan_id":"10544143-2b56-45b4-8c7a-cf42198f6b9e","yayasan":"NUSANTARA","sk_izin_operasional":"-","tanggal_sk_izin_operasional":null,"no_rekening":"3004192868","nama_bank":"BPD JAMBI","cabang_kcp_unit":"Cabang Ma Bungo","rekening_atas_nama":"69791950 KB NUSANTARA","mbs":0,"luas_tanah_milik":0,"luas_tanah_bukan_milik":180,"kode_registrasi":"239689208329326","npwp":"793152422332000               ","nm_wp":null,"keaktifan":"1","flag":null,"daya_listrik":900,"kontinuitas_listrik":"1","jarak_listrik":0,"wilayah_terpencil":"0","wilayah_perbatasan":"0","wilayah_transmigrasi":"0","wilayah_adat_terpencil":"0","wilayah_bencana_alam":"0","wilayah_bencana_sosial":"0","partisipasi_bos":"1","waktu_penyelenggaraan_id":1,"waktu_penyelenggaraan":"Pagi/6 hari","sumber_listrik_id":2,"sumber_listrik":"PLN","sertifikasi_iso_id":9,"sertifikasi_iso":"Belum Bersertifikat","akses_internet_id":0,"akses_internet":"Tidak Ada","akses_internet_2_id":0,"akses_internet_2":"Tidak Ada","akreditasi":"C","create_date":"2018-02-06T22:59:03.437000","last_update":"2019-05-07T11:00:00"},{"sekolah_id":"01578273-186b-4f04-b78b-4f436be97db9","semester_id":"20222","nama":"KB UNGU","nama_nomenklatur":null,"nss":"****        ","npsn":"69791934","bentuk_pendidikan_id":2,"bentuk_pendidikan":"KB","alamat_jalan":"KAMPUNG KAPAS","rt":null,"rw":null,"nama_dusun":"Lubuk Landai","kode_wilayah":"100299AE","kode_desa_kelurahan":"100299AE","desa_kelurahan":"Lubuk Landai","kode_kecamatan":"100299  ","kecamatan":"Kec. Tanah Sepenggal Lintas","kode_kabupaten":"100200  ","kabupaten":"Kab. Bungo","kode_provinsi":"100000  ","provinsi":"Prov. Jambi","kode_pos":"37263","lintang":-1.410013,"bujur":101.944885,"nomor_telepon":"082357910324","nomor_fax":null,"email":"paudungu@gmail.com","website":"http://","kebutuhan_khusus_id":0,"kebutuhan_khusus":"Tidak ada","status_sekolah_id":"2","status_sekolah":"SWASTA","sk_pendirian_sekolah":"110","tanggal_sk_pendirian":"2008-01-02","status_kepemilikan_id":4,"status_kepemilikan":"Lainnya","yayasan_id":"2824e322-027c-4d5b-8ea8-de060464cc1f","yayasan":"KB UNGU","sk_izin_operasional":"1100 TAHUN 2008","tanggal_sk_izin_operasional":"2008-01-02","no_rekening":"3004192701","nama_bank":"BPD JAMBI","cabang_kcp_unit":"Cabang Ma Bungo","rekening_atas_nama":"69791934 KB UNGU","mbs":0,"luas_tanah_milik":0,"luas_tanah_bukan_milik":800,"kode_registrasi":"127003642653464","npwp":"028755122332000               ","nm_wp":null,"keaktifan":"1","flag":null,"daya_listrik":900,"kontinuitas_listrik":"1","jarak_listrik":0,"wilayah_terpencil":"0","wilayah_perbatasan":"0","wilayah_transmigrasi":"0","wilayah_adat_terpencil":"0","wilayah_bencana_alam":"0","wilayah_bencana_sosial":"0","partisipasi_bos":"1","waktu_penyelenggaraan_id":1,"waktu_penyelenggaraan":"Pagi/6 hari","sumber_listrik_id":2,"sumber_listrik":"PLN","sertifikasi_iso_id":9,"sertifikasi_iso":"Belum Bersertifikat","akses_internet_id":0,"akses_internet":"Tidak Ada","akses_internet_2_id":4,"akses_internet_2":"Telkomsel Flash","akreditasi":"B","create_date":"2018-02-06T22:59:03.437000","last_update":"2022-03-10T11:08:09.470000"},{"sekolah_id":"71cd1ca9-79b7-4739-ba8d-f2945cf5f1cf","semester_id":"20222","nama":"KB TUNAS HARAPAN","nama_nomenklatur":null,"nss":"****        ","npsn":"69886807","bentuk_pendidikan_id":2,"bentuk_pendidikan":"KB","alamat_jalan":"LINTAS SUMATERA KM 24 ARAH PADANG","rt":9,"rw":null,"nama_dusun":"balai panjang","kode_wilayah":"100299AB","kode_desa_kelurahan":"100299AB","desa_kelurahan":"TANAH PERIUK","kode_kecamatan":"100299  ","kecamatan":"Kec. Tanah Sepenggal Lintas","kode_kabupaten":"100200  ","kabupaten":"Kab. Bungo","kode_provinsi":"100000  ","provinsi":"Prov. Jambi","kode_pos":"37263","lintang":0.0,"bujur":0.0,"nomor_telepon":null,"nomor_fax":null,"email":"tunaspaud@yahoo.com","website":"http://","kebutuhan_khusus_id":0,"kebutuhan_khusus":"Tidak ada","status_sekolah_id":"2","status_sekolah":"SWASTA","sk_pendirian_sekolah":null,"tanggal_sk_pendirian":null,"status_kepemilikan_id":3,"status_kepemilikan":"Yayasan","yayasan_id":"d78256f0-64a2-4a0f-ac02-1a0f614f008b","yayasan":"PAUD TUNAS HARAPAN","sk_izin_operasional":"1191 TAHUN 2008","tanggal_sk_izin_operasional":null,"no_rekening":"3004193104","nama_bank":"BPD JAMBI","cabang_kcp_unit":"Cabang Ma Bungo","rekening_atas_nama":"69886807 KB TUNAS HARAPAN","mbs":0,"luas_tanah_milik":0,"luas_tanah_bukan_milik":700,"kode_registrasi":"185941170960249","npwp":"026938365332000               ","nm_wp":null,"keaktifan":"1","flag":null,"daya_listrik":0,"kontinuitas_listrik":"1","jarak_listrik":0,"wilayah_terpencil":"0","wilayah_perbatasan":"0","wilayah_transmigrasi":"0","wilayah_adat_terpencil":"0","wilayah_bencana_alam":"0","wilayah_bencana_sosial":"0","partisipasi_bos":"1","waktu_penyelenggaraan_id":1,"waktu_penyelenggaraan":"Pagi/6 hari","sumber_listrik_id":7,"sumber_listrik":"Menumpang","sertifikasi_iso_id":9,"sertifikasi_iso":"Belum Bersertifikat","akses_internet_id":4,"akses_internet":"Telkomsel Flash","akses_internet_2_id":4,"akses_internet_2":"Telkomsel Flash","akreditasi":"C","create_date":"2018-02-06T22:59:03.437000","last_update":"2022-03-10T11:08:09.470000"},{"sekolah_id":"00fb7f5d-0c26-e111-87e9-a3090e2445fe","semester_id":"20222","nama":"SD NEGERI 029II SUNGAI MANCUR","nama_nomenklatur":null,"nss":"101100215028","npsn":"10500962","bentuk_pendidikan_id":5,"bentuk_pendidikan":"SD","alamat_jalan":"Sungai Mancur","rt":8,"rw":4,"nama_dusun":"SUNGAI MANCUR","kode_wilayah":"100299AD","kode_desa_kelurahan":"100299AD","desa_kelurahan":"Sungai Mancur","kode_kecamatan":"100299  ","kecamatan":"Kec. Tanah Sepenggal Lintas","kode_kabupaten":"100200  ","kabupaten":"Kab. Bungo","kode_provinsi":"100000  ","provinsi":"Prov. Jambi","kode_pos":"37263","lintang":-1.4148,"bujur":101.9955,"nomor_telepon":"085384545780","nomor_fax":null,"email":"sdnduasembilanmancur@gmail.com","website":null,"kebutuhan_khusus_id":0,"kebutuhan_khusus":"Tidak ada","status_sekolah_id":"1","status_sekolah":"NEGERI","sk_pendirian_sekolah":"","tanggal_sk_pendirian":"1957-01-01","status_kepemilikan_id":2,"status_kepemilikan":"Pemerintah Daerah","yayasan_id":null,"yayasan":null,"sk_izin_operasional":"-","tanggal_sk_izin_operasional":"1910-01-01","no_rekening":"3720055615","nama_bank":"POS Indonesia","cabang_kcp_unit":"Muara Bungo","rekening_atas_nama":"SDN 29/II SUNGAI MANCUR","mbs":1,"luas_tanah_milik":3926,"luas_tanah_bukan_milik":0,"kode_registrasi":"220825660448456","npwp":"001155928332000               ","nm_wp":null,"keaktifan":"1","flag":"3  ","daya_listrik":1300,"kontinuitas_listrik":"1","jarak_listrik":0,"wilayah_terpencil":"0","wilayah_perbatasan":"0","wilayah_transmigrasi":"0","wilayah_adat_terpencil":"0","wilayah_bencana_alam":"0","wilayah_bencana_sosial":"0","partisipasi_bos":"1","waktu_penyelenggaraan_id":1,"waktu_penyelenggaraan":"Pagi/6 hari","sumber_listrik_id":2,"sumber_listrik":"PLN","sertifikasi_iso_id":9,"sertifikasi_iso":"Belum Bersertifikat","akses_internet_id":4,"akses_internet":"Telkomsel Flash","akses_internet_2_id":4,"akses_internet_2":"Telkomsel Flash","akreditasi":"B","create_date":"2018-01-24T12:09:39.813000","last_update":"2023-03-13T13:40:42.090000"}]